Workbook

Sheet Supplier Profile & Audit Plan
A1: VSAC-Report-Template-2021 V1c | C1: Red text = Required
A2: Supplier to complete light-green cells | C2: Vertiv to complete light-yellow cells
A3: Vertiv Supplier Audit Checklist
A4: Supplier Profile & Audit Plan
E5: 1.0 SUPPLIER PROFILE (Supplier to Complete)
A6: Savannah Tank & Equipment Corp. | E6: Supplier (Company name)
E7: Facility Address
E8: Facility Address (cont)
E9: City
E10: State / Province
E11: Country
E12: Mail/PIN Code
E13: Supplier's Telephone No.
E14: Supplier's Web-site
E15: Year Started Operations
E16: Other Location 1
E17: Other Location 2
E18: Other Location 3
A19: Name | B19: Phone | C19: email Address | E19: Supplier Contacts
E20: President
E21: Plant Manager
E22: Quality Manager
E23: Customer Service Manager
E24: Sales Manager
E25: Engineering Manager
E26: Other - Type Title here.
E27: Other - Type Title here.
E28: Annual Sales (USD)
E29: Capacity/Year (Units)
E30: Plant Size (total)
E31: Actual Capacity
... E37: Contract Expiration
A38: Quality System Certification Status | E38: Quality System Certification Status
E39: Quality Standard
E40: Location Certified
E41: Expiration Date
E42: ISO / TS Registrar
E43: Accreditation Body
E44: 2.0 AUDIT PLAN (Vertiv to Complete)
A45: AMER | E45: Vertiv Region
E46: Supplier Self-Audit Date(mm/dd/yyyy)
A47: TBD | E47: On-Site Audit Date (mm/dd/yyyy)
E48: Corrective Action Verification Date (mm/dd/yyyy)
A49: Sheet Metal & Enclosure | E49: Commodity Family (Primary / Secondary)
E50: Supplier Code
A51: New Supplier | E51: Purpose of Audit
E52: Project Reference
A53: Contact #1 | B53: Contact #2 | C53: Contact #3 | D53: Contact #4 | E53: Vertiv Contacts
A54: Aaron Allen | E54: Name
A55: Americas IS Supplier Quality Engineer | E55: Title
A56: 740-688-9240 | E56: Contact Phone No.
A57: aaron.allen@vertiv.com | E57: Email Address
E58: 3.0 DOCUMENTATION NEEDED (Vertiv to Complete)
A59: NOTES | C59: REQUESTED | D59: RECEIVED | E59: Requested / Received
A60: x = submitted with self audit; typically 7 working days prior to audit A = available at the time of the audit TBD = as required by commodity | C60: X | E60: Quality Manual (typically is policy manual - not work instructions)
C61: X | E61: ISO / TS Certificate (must state registrar & accreditation body)
C62: X | E62: Supplier Profile (or similar form provided by auditing Division)
C63: X | E63: Supplier Self-Audit (VSAC)
C64: X | E64: Major Customers & Competitors
C65: X | E65: Test & Inspection Equipment List
C66: X | E66: Quality Organizational Chart
C67: X | E67: Process Quality Control Plan
E68: Process Capability Study
E69: Reliability Test Plan
C70: X | E70: Major Suppliers and Raw Materials List
C71: X | E71: Regulatory Agency Certificates, as applicable
E72: Other (If Applicable)
E73: 4.0 PERSONNEL INVOLVED IN AUDIT (Vertiv to Complete)
A74: Vertiv Audit Team | E74: Vertiv Audit Team
A75: First Name | B75: Last Name | C75: Title | E75: First Name / Last Name / Title
A76: Aaron | B76: Allen | C76: Americas IS SQE | E76: Lead Auditor
A82: Supplier Personnel | E82: Supplier Personnel Involved in Audit
A83: First Name | B83: Last Name | C83: Title | E83: First Name / Last Name / Title
A107: Hide
A108: Auditing Division | B108: Commodity Name | C108: Country
A110: AMER | B110: Cable & Wire harness | C110: American Samoa
A111: EMEA | B111: Sheet Metal & Enclosure | C111: Argentina
A112: CHINA | B112: Coil | C112: Australia
A113: INDIA | B113: Transformer | C113: Austria
A114: ROA | B114: EMS (PCBA) | C114: Azerbaijan
B115: Battery | C115: Bahrain
B116: Fans And Blowers | C116: Belarus
B117: Compressor | C117: Belgium
B118: Bus Bar | C118: Bermuda
B119: Casting: Aluminum/Zinc | C119: Bolivia
B120: Casting: Ductile Iron | C120: Brazil
B121: Casting: Grey Iron | C121: Brunei Darussalam
B122: Casting: Malleable Iron | C122: Bulgaria
B123: Casting: Other | C123: Canada
B124: Casting: Sst/Alloy | C124: China
B125: Casting: Steel/Sst | C125: Colombia
B126: Circuit Breaker | C126: Costa Rica
... B196: Wire Form Or Wire Cloth | C196: Venezuela
C197: Vietnam
C198: Virgin Islands, British
A321: Hide

Sheet Checklist
D1: Supplier to complete light-green cells | E1: Vertiv to complete light-yellow cells | F1: Not Applicable | G1: Not Verified | H1: =COUNTIF(H7:H86,100) -> 0 | I1: =COUNTIF(I7:I86,100) -> 0 | J1: =COUNTIF(J7:J86,100) -> 0 | K1: =IF(SUM($I$1:$J$1)>=2,"Refer to VSAC Auditor Scoring Guide when using score of '100'.","") | M1: VSAC-Report-Template-2021 V1c | T1: Correct Row Order | W1: Hide >> | AB1: Supplier Self-Audit | AC1: 0 | AD1: 40 | AE1: 60 | AF1: 70 | AG1: 80 | AH1: 100 | AI1: Status | AJ1: << Hide
W2: Hide >> | AB2: On-Site Audit | AC2: 0 | AD2: 40 | AE2: 60 | AF2: 70 | AG2: 80 | AH2: 100 | AI2: Open | AJ2: << Hide
D3: STANDARD CHECKLIST | E3: =IF('Supplier Profile & Audit Plan'!$A$6="","",'Supplier Profile & Audit Plan'!$A$6) -> Savannah Tank & Equipment Corp. | H3: Supplier Self Audit SCORE | I3: On-Site Audit SCORE | J3: After CA Verif. SCORE | K3: AUDIT FINDINGS & OBSERVATIONS | L3: Supplier CA Req'd? (Y / N) | M3: Completion Date (mm/dd/yyyy) | N3: CA Status | O3: ROOT CAUSE & Scope of Problem Including Other Areas | P3: REMEDIAL ACTION Immediate Actions Taken to Address Issue / Finding | Q3: CORRECTIVE ACTION Taken to Address Root Cause & Prevent Recurrence | R3: PREVENTIVE ACTION Actions Taken to Prevent Similar Issues in Other Areas | S3: CONTROLS Deployed to Monitor CA/PA Effectiveness | W3: Hide >> | X3: Supp. Score (w/o n/a's) | Y3: On-Site Score (w/o n/a's) | Z3: After Verif .Score (w/o n/a's) | AB3: Adjusted | AC3: 0 | AD3: 40 | AE3: 60 | AF3: 70 | AG3: 80 | AH3: 100 | AI3: Closed | AJ3: << Hide
D4: =IF('Supplier Profile & Audit Plan'!$A$47>0,'Supplier Profile & Audit Plan'!$A$47,'Supplier Profile & Audit Plan'!$A$46) -> TBD | E4: =IF('Supplier Profile & Audit Plan'!$A$49="","",'Supplier Profile & Audit Plan'!$A$49) -> Sheet Metal & Enclosure | W4: Hide >> | AI4: <blank> | AJ4: << Hide
D5: Requirements | E5: Typical Objective Evidence | W5: Hide >> | AJ5: << Hide
D6: Go to: Findings | E6: Go to: Corrective Actions | K6: Go to: Scoring Guidelines | O6: Go to: Corrective Action Instructions | W6: Hide >> | AJ6: << Hide
A7: Bottom | B7: 1.0 QUALITY MANAGEMENT | C7: 1.1 | D7: The quality system is documented, controlled, and maintained to clearly describe current practice. Documented procedures required. Records required. | E7: Quality manual and all QS procedures show revision control (sign-offs & dates), history of changes. | L7: =IF(I7="","",IF(F7<>"","",IF(I7>=70,"N","Y"))) | N7: =IF(I7="","",IF(I7>=70,"",IF(SUM(IF(I7>=70,1,-1)+IF(J7>=70,1,-1))>=0,"Closed","Open"))) | T7: 1 | W7: Hide >> | X7: =IF(COUNTA($F7,$G7)>0,"n/a",IF(H7="","",H7)) | Y7: =IF(COUNTA($F7,$G7)>0,"n/a",IF(I7="","",I7)) | Z7: =IF(COUNTA($F7,$G7)>0,"n/a",IF(J7="","",J7)) | AJ7: << Hide
A8: 1 | C8: 1.2 | D8: Organizational development with roles and responsibilities should be in place to support business strategy and operations. Quality function should be clear. | E8: Business strategy (or plan), organization chart. | L8: =IF(I8="","",IF(F8<>"","",IF(I8>=70,"N","Y"))) | N8: =IF(I8="","",IF(I8>=70,"",IF(SUM(IF(I8>=70,1,-1)+IF(J8>=70,1,-1))>=0,"Closed","Open"))) | T8: 2 | W8: Hide >> | X8: =IF(COUNTA($F8,$G8)>0,"n/a",IF(H8="","",H8)) | Y8: =IF(COUNTA($F8,$G8)>0,"n/a",IF(I8="","",I8)) | Z8: =IF(COUNTA($F8,$G8)>0,"n/a",IF(J8="","",J8)) | AJ8: << Hide
A9: 2 | C9: 1.3 | D9: Quality reports, trend charts and data analysis identify areas of opportunity and are used by management on a routine basis. Records required. | E9: Product quality yield data, top problems and corresponding improvement actions, status of preventive/corrective actions taken, internal audit results, records of customer quality issues and resolution | L9: =IF(I9="","",IF(F9<>"","",IF(I9>=70,"N","Y"))) | N9: =IF(I9="","",IF(I9>=70,"",IF(SUM(IF(I9>=70,1,-1)+IF(J9>=70,1,-1))>=0,"Closed","Open"))) | T9: 3 | W9: Hide >> | X9: =IF(COUNTA($F9,$G9)>0,"n/a",IF(H9="","",H9)) | Y9: =IF(COUNTA($F9,$G9)>0,"n/a",IF(I9="","",I9)) | Z9: =IF(COUNTA($F9,$G9)>0,"n/a",IF(J9="","",J9)) | AJ9: << Hide
A10: 3 | C10: 1.4 | D10: Quality performance targets are clearly defined, included in the business plan and monitored for improvements. | E10: Strategic and tactical objectives, goals, action plans, etc. | L10: =IF(I10="","",IF(F10<>"","",IF(I10>=70,"N","Y"))) | N10: =IF(I10="","",IF(I10>=70,"",IF(SUM(IF(I10>=70,1,-1)+IF(J10>=70,1,-1))>=0,"Closed","Open"))) | T10: 4 | W10: Hide >> | X10: =IF(COUNTA($F10,$G10)>0,"n/a",IF(H10="","",H10)) | Y10: =IF(COUNTA($F10,$G10)>0,"n/a",IF(I10="","",I10)) | Z10: =IF(COUNTA($F10,$G10)>0,"n/a",IF(J10="","",J10)) | AJ10: << Hide
A11: 4 | C11: 1.5 | D11: Quality records are maintained. A record control system is in place for the identification, storage, protection, retrieval, retention time, and disposition of quality records. | E11: Procedures, list of records to be kept with retention periods specified | L11: =IF(I11="","",IF(F11<>"","",IF(I11>=70,"N","Y"))) | N11: =IF(I11="","",IF(I11>=70,"",IF(SUM(IF(I11>=70,1,-1)+IF(J11>=70,1,-1))>=0,"Closed","Open"))) | T11: 5 | W11: Hide >> | X11: =IF(COUNTA($F11,$G11)>0,"n/a",IF(H11="","",H11)) | Y11: =IF(COUNTA($F11,$G11)>0,"n/a",IF(I11="","",I11)) | Z11: =IF(COUNTA($F11,$G11)>0,"n/a",IF(J11="","",J11)) | AJ11: << Hide
A12: 5 | C12: 1.6 | D12: Executive management participates in periodic quality system reviews that address quality related feedback from customers and internal quality metrics. Records required. | E12: Analysis of field failures, inspection yields, resource needs, internal audit results, corrective action status, etc. Evidence of regularly scheduled executive management review of performance | L12: =IF(I12="","",IF(F12<>"","",IF(I12>=70,"N","Y"))) | N12: =IF(I12="","",IF(I12>=70,"",IF(SUM(IF(I12>=70,1,-1)+IF(J12>=70,1,-1))>=0,"Closed","Open"))) | T12: 6 | W12: Hide >> | X12: =IF(COUNTA($F12,$G12)>0,"n/a",IF(H12="","",H12)) | Y12: =IF(COUNTA($F12,$G12)>0,"n/a",IF(I12="","",I12)) | Z12: =IF(COUNTA($F12,$G12)>0,"n/a",IF(J12="","",J12)) | AJ12: << Hide
A13: 6 | B13: 2.0 CONTINUOUS IMPROVEMENT | C13: 2.1 | D13: Improvement actions are taken based on the analysis of significant business trends, design reviews, customer satisfaction surveys or other meaningful inputs. Documented procedures required. Records required. | E13: Management review meetings, goal setting, performance measurement, internal audits, action plans, customer surveys | L13: =IF(I13="","",IF(F13<>"","",IF(I13>=70,"N","Y"))) | N13: =IF(I13="","",IF(I13>=70,"",IF(SUM(IF(I13>=70,1,-1)+IF(J13>=70,1,-1))>=0,"Closed","Open"))) | T13: 7 | W13: Hide >> | X13: =IF(COUNTA($F13,$G13)>0,"n/a",IF(H13="","",H13)) | Y13: =IF(COUNTA($F13,$G13)>0,"n/a",IF(I13="","",I13)) | Z13: =IF(COUNTA($F13,$G13)>0,"n/a",IF(J13="","",J13)) | AJ13: << Hide
A14: 7 | C14: 2.2 | D14: A formal approach is used to actively pursue cost containment and other continual improvement activities throughout the organization. Documented procedures required. Records required. | E14: Employee involvement / recognition program, Lean, Six Sigma, kaizen, SIC, 5-S, cost reduction program, preventive actions | L14: =IF(I14="","",IF(F14<>"","",IF(I14>=70,"N","Y"))) | N14: =IF(I14="","",IF(I14>=70,"",IF(SUM(IF(I14>=70,1,-1)+IF(J14>=70,1,-1))>=0,"Closed","Open"))) | T14: 8 | W14: Hide >> | X14: =IF(COUNTA($F14,$G14)>0,"n/a",IF(H14="","",H14)) | Y14: =IF(COUNTA($F14,$G14)>0,"n/a",IF(I14="","",I14)) | Z14: =IF(COUNTA($F14,$G14)>0,"n/a",IF(J14="","",J14)) | AJ14: << Hide
A15: 8 | C15: 2.3 | D15: A corrective action system is in place that provides root cause analysis and takes timely and effective action to prevent recurrence. Documented procedures required. Records required. | E15: Corrective action records, trend charts, meeting minutes, nonconformance frequency & cost analysis. Does CA system cover customer, internal & supplier issues? | L15: =IF(I15="","",IF(F15<>"","",IF(I15>=70,"N","Y"))) | N15: =IF(I15="","",IF(I15>=70,"",IF(SUM(IF(I15>=70,1,-1)+IF(J15>=70,1,-1))>=0,"Closed","Open"))) | T15: 9 | W15: Hide >> | X15: =IF(COUNTA($F15,$G15)>0,"n/a",IF(H15="","",H15)) | Y15: =IF(COUNTA($F15,$G15)>0,"n/a",IF(I15="","",I15)) | Z15: =IF(COUNTA($F15,$G15)>0,"n/a",IF(J15="","",J15)) | AJ15: << Hide
A16: 9 | C16: 2.4 | D16: Contingency plans (risk mitigation) have been developed that describe actions to be taken in the event of a major interruption of facility and / or the manufacturing process. | E16: Process covering natural disasters, utility interruptions, labor shortages, key equipment failures, major production issues. | L16: =IF(I16="","",IF(F16<>"","",IF(I16>=70,"N","Y"))) | N16: =IF(I16="","",IF(I16>=70,"",IF(SUM(IF(I16>=70,1,-1)+IF(J16>=70,1,-1))>=0,"Closed","Open"))) | T16: 10 | W16: Hide >> | X16: =IF(COUNTA($F16,$G16)>0,"n/a",IF(H16="","",H16)) | Y16: =IF(COUNTA($F16,$G16)>0,"n/a",IF(I16="","",I16)) | Z16: =IF(COUNTA($F16,$G16)>0,"n/a",IF(J16="","",J16)) | AJ16: << Hide
A17: 10 | B17: 3.0 COMPETENCE DEVELOPMENT | C17: 3.1 | D17: The skill and education level required for each job is documented and appropriate training / re-training is provided. Records required. | E17: Job descriptions, job skills assessment, training records, training manuals. Look for use of training aids & work instructions at work stations. | L17: =IF(I17="","",IF(F17<>"","",IF(I17>=70,"N","Y"))) | N17: =IF(I17="","",IF(I17>=70,"",IF(SUM(IF(I17>=70,1,-1)+IF(J17>=70,1,-1))>=0,"Closed","Open"))) | T17: 11 | W17: Hide >> | X17: =IF(COUNTA($F17,$G17)>0,"n/a",IF(H17="","",H17)) | Y17: =IF(COUNTA($F17,$G17)>0,"n/a",IF(I17="","",I17)) | Z17: =IF(COUNTA($F17,$G17)>0,"n/a",IF(J17="","",J17)) | AJ17: << Hide
A18: 11 | C18: 3.2 | D18: Employee qualification / certification is maintained where the quality outcome of the process cannot be verified and is strongly dependent upon operator skill. Records required. | E18: Qualification records, certification history, etc. | L18: =IF(I18="","",IF(F18<>"","",IF(I18>=70,"N","Y"))) | N18: =IF(I18="","",IF(I18>=70,"",IF(SUM(IF(I18>=70,1,-1)+IF(J18>=70,1,-1))>=0,"Closed","Open"))) | T18: 12 | W18: Hide >> | X18: =IF(COUNTA($F18,$G18)>0,"n/a",IF(H18="","",H18)) | Y18: =IF(COUNTA($F18,$G18)>0,"n/a",IF(I18="","",I18)) | Z18: =IF(COUNTA($F18,$G18)>0,"n/a",IF(J18="","",J18)) | AJ18: << Hide
A19: 12 | C19: 3.3 | D19: Suitable methods are used to verify training effectiveness. Records required. | E19: Records of student testing, production quality records, audit records, interview workers to validate training records. Look for use of training aids & work instructions at work stations. | L19: =IF(I19="","",IF(F19<>"","",IF(I19>=70,"N","Y"))) | N19: =IF(I19="","",IF(I19>=70,"",IF(SUM(IF(I19>=70,1,-1)+IF(J19>=70,1,-1))>=0,"Closed","Open"))) | T19: 13 | W19: Hide >> | X19: =IF(COUNTA($F19,$G19)>0,"n/a",IF(H19="","",H19)) | Y19: =IF(COUNTA($F19,$G19)>0,"n/a",IF(I19="","",I19)) | Z19: =IF(COUNTA($F19,$G19)>0,"n/a",IF(J19="","",J19)) | AJ19: << Hide
A20: 13 | B20: 4.0 DESIGN AND DEVELOPMENT OF PRODUCTS AND SERVICES | C20: 4.1 | D20: Customer needs and requirements are incorporated into product designs and/or manufacturing processes. Critical-to-Quality (CTQ) characteristics are identified and understood. Records required. | E20: Market studies, customer/end-user surveys, technical design reviews, mfg process capability studies, formal process qualification plan, manufacturing verification tests, pilot runs, Procedures, design / process review minutes, FMEA's, etc. | L20: =IF(I20="","",IF(F20<>"","",IF(I20>=70,"N","Y"))) | N20: =IF(I20="","",IF(I20>=70,"",IF(SUM(IF(I20>=70,1,-1)+IF(J20>=70,1,-1))>=0,"Closed","Open"))) | T20: 14 | W20: Hide >> | X20: =IF(COUNTA($F20,$G20)>0,"n/a",IF(H20="","",H20)) | Y20: =IF(COUNTA($F20,$G20)>0,"n/a",IF(I20="","",I20)) | Z20: =IF(COUNTA($F20,$G20)>0,"n/a",IF(J20="","",J20)) | AJ20: << Hide
A21: 14 | C21: 4.2 | D21: Product specifications and drawings are generated, controlled and maintained for new or changed product designs. Records required. | E21: Complete product characteristics, application requirements, and other information essential for its safe and proper use and eventual disposal, etc. | L21: =IF(I21="","",IF(F21<>"","",IF(I21>=70,"N","Y"))) | N21: =IF(I21="","",IF(I21>=70,"",IF(SUM(IF(I21>=70,1,-1)+IF(J21>=70,1,-1))>=0,"Closed","Open"))) | T21: 15 | W21: Hide >> | X21: =IF(COUNTA($F21,$G21)>0,"n/a",IF(H21="","",H21)) | Y21: =IF(COUNTA($F21,$G21)>0,"n/a",IF(I21="","",I21)) | Z21: =IF(COUNTA($F21,$G21)>0,"n/a",IF(J21="","",J21)) | AJ21: << Hide
A22: 15 | C22: 4.3 | D22: Design validation is an integral part of the design process and occurs prior to production release.Approval mechanism is clear. Records required. | E22: Design results, manufacturability, productivity and cost studies, confirmation that product fulfills its specified requirements or intended use or applications, design-FMEA, etc. | L22: =IF(I22="","",IF(F22<>"","",IF(I22>=70,"N","Y"))) | N22: =IF(I22="","",IF(I22>=70,"",IF(SUM(IF(I22>=70,1,-1)+IF(J22>=70,1,-1))>=0,"Closed","Open"))) | T22: 16 | W22: Hide >> | X22: =IF(COUNTA($F22,$G22)>0,"n/a",IF(H22="","",H22)) | Y22: =IF(COUNTA($F22,$G22)>0,"n/a",IF(I22="","",I22)) | Z22: =IF(COUNTA($F22,$G22)>0,"n/a",IF(J22="","",J22)) | AJ22: << Hide
A23: 16 | C23: 4.4 | D23: Human and technical resources are adequate to meet Vertiv’s requirements for design collaboration, tooling design and electronic drawing and data exchange. NPI project team is clearly developed. | E23: Qualification of technical staff. Equipment/software capabilities; CAD, PRO-E, etc. Experience, equipment and technical knowledge for products to be produced for Vertiv NPI project organization chart | L23: =IF(I23="","",IF(F23<>"","",IF(I23>=70,"N","Y"))) | N23: =IF(I23="","",IF(I23>=70,"",IF(SUM(IF(I23>=70,1,-1)+IF(J23>=70,1,-1))>=0,"Closed","Open"))) | T23: 17 | W23: Hide >> | X23: =IF(COUNTA($F23,$G23)>0,"n/a",IF(H23="","",H23)) | Y23: =IF(COUNTA($F23,$G23)>0,"n/a",IF(I23="","",I23)) | Z23: =IF(COUNTA($F23,$G23)>0,"n/a",IF(J23="","",J23)) | AJ23: << Hide
A24: 17 | C24: 4.5 | D24: New and revised customer specifications are reviewed and implemented in a timely manner. | E24: Technical review of methods to be used, capability studies on similar parts, documented review procedure, PPAP process, APQP (e.g. DFA, design reviews, process quality system review, packaging evaluation, etc) | L24: =IF(I24="","",IF(F24<>"","",IF(I24>=70,"N","Y"))) | N24: =IF(I24="","",IF(I24>=70,"",IF(SUM(IF(I24>=70,1,-1)+IF(J24>=70,1,-1))>=0,"Closed","Open"))) | T24: 18 | W24: Hide >> | X24: =IF(COUNTA($F24,$G24)>0,"n/a",IF(H24="","",H24)) | Y24: =IF(COUNTA($F24,$G24)>0,"n/a",IF(I24="","",I24)) | Z24: =IF(COUNTA($F24,$G24)>0,"n/a",IF(J24="","",J24)) | AJ24: << Hide
A25: 18 | C25: 4.6 | D25: Process and quality control documents are well in place and used for production start-up, as important deliverables transisioning from NPI to production ramp up. | E25: Customer specifications, engineering drawings, change notices, work instructions and specifications as applicable, documented procedures | L25: =IF(I25="","",IF(F25<>"","",IF(I25>=70,"N","Y"))) | N25: =IF(I25="","",IF(I25>=70,"",IF(SUM(IF(I25>=70,1,-1)+IF(J25>=70,1,-1))>=0,"Closed","Open"))) | T25: 19 | W25: Hide >> | X25: =IF(COUNTA($F25,$G25)>0,"n/a",IF(H25="","",H25)) | Y25: =IF(COUNTA($F25,$G25)>0,"n/a",IF(I25="","",I25)) | Z25: =IF(COUNTA($F25,$G25)>0,"n/a",IF(J25="","",J25)) | AJ25: << Hide
A26: Bottom | C26: 4.7 | D26: Customer notification / approval occurs for changes to Control Plans, manufacturing site, product transfers, raw material or product obsolescence. Records required. | E26: Customer notification procedure/evidence on major changes, signed material / process change requests | L26: =IF(I26="","",IF(F26<>"","",IF(I26>=70,"N","Y"))) | N26: =IF(I26="","",IF(I26>=70,"",IF(SUM(IF(I26>=70,1,-1)+IF(J26>=70,1,-1))>=0,"Closed","Open"))) | T26: 20 | W26: Hide >> | X26: =IF(COUNTA($F26,$G26)>0,"n/a",IF(H26="","",H26)) | Y26: =IF(COUNTA($F26,$G26)>0,"n/a",IF(I26="","",I26)) | Z26: =IF(COUNTA($F26,$G26)>0,"n/a",IF(J26="","",J26)) | AJ26: << Hide
A27: 1 | B27: 5.0 QUALITY PLANNING | C27: 5.1 | D27: Production samples are inspected and provided to customers upon request. Records required. | E27: Completed PPAP or similar forms, inspection reports, availability of qualified resources | L27: =IF(I27="","",IF(F27<>"","",IF(I27>=70,"N","Y"))) | N27: =IF(I27="","",IF(I27>=70,"",IF(SUM(IF(I27>=70,1,-1)+IF(J27>=70,1,-1))>=0,"Closed","Open"))) | T27: 21 | W27: Hide >> | X27: =IF(COUNTA($F27,$G27)>0,"n/a",IF(H27="","",H27)) | Y27: =IF(COUNTA($F27,$G27)>0,"n/a",IF(I27="","",I27)) | Z27: =IF(COUNTA($F27,$G27)>0,"n/a",IF(J27="","",J27)) | AJ27: << Hide
A28: 2 | C28: 5.2 | D28: Reliability test plans are developed and routinely followed. Testing is used to verify design spec's, drive design improvements and provide an on-going check of materials and workmanship. Documented procedures required. Records required. | E28: Reliability test plans, test reports, improvement/corrective actions taken, design changes implemented | L28: =IF(I28="","",IF(F28<>"","",IF(I28>=70,"N","Y"))) | N28: =IF(I28="","",IF(I28>=70,"",IF(SUM(IF(I28>=70,1,-1)+IF(J28>=70,1,-1))>=0,"Closed","Open"))) | T28: 22 | W28: Hide >> | X28: =IF(COUNTA($F28,$G28)>0,"n/a",IF(H28="","",H28)) | Y28: =IF(COUNTA($F28,$G28)>0,"n/a",IF(I28="","",I28)) | Z28: =IF(COUNTA($F28,$G28)>0,"n/a",IF(J28="","",J28)) | AJ28: << Hide
A29: 3 | C29: 5.3 | D29: Product reliability test data is available upon request and historical test performance data shows a highly stable process and product design. Records required. | E29: Reliability test summary reports/charts | L29: =IF(I29="","",IF(F29<>"","",IF(I29>=70,"N","Y"))) | N29: =IF(I29="","",IF(I29>=70,"",IF(SUM(IF(I29>=70,1,-1)+IF(J29>=70,1,-1))>=0,"Closed","Open"))) | T29: 23 | W29: Hide >> | X29: =IF(COUNTA($F29,$G29)>0,"n/a",IF(H29="","",H29)) | Y29: =IF(COUNTA($F29,$G29)>0,"n/a",IF(I29="","",I29)) | Z29: =IF(COUNTA($F29,$G29)>0,"n/a",IF(J29="","",J29)) | AJ29: << Hide
A30: 4 | B30: 6.0 PROCUREMENT | C30: 6.1 | D30: A formal process is used for the selection, qualification and re-qualification of suppliers. Records required. | E30: Supplier quality system audits and related corrective actions, engineering testing and approval records, plant production trials | L30: =IF(I30="","",IF(F30<>"","",IF(I30>=70,"N","Y"))) | N30: =IF(I30="","",IF(I30>=70,"",IF(SUM(IF(I30>=70,1,-1)+IF(J30>=70,1,-1))>=0,"Closed","Open"))) | T30: 24 | W30: Hide >> | X30: =IF(COUNTA($F30,$G30)>0,"n/a",IF(H30="","",H30)) | Y30: =IF(COUNTA($F30,$G30)>0,"n/a",IF(I30="","",I30)) | Z30: =IF(COUNTA($F30,$G30)>0,"n/a",IF(J30="","",J30)) | AJ30: << Hide
A31: 5 | C31: 6.2 | D31: Purchases from unapproved suppliers are prevented by a properly controlled and available Approved Supplier List (ASL). Records required. | E31: ASL, procedures for control and use of ASL, production material receipt records, counterfeit part prevention measures in place as appropriate/applicable | L31: =IF(I31="","",IF(F31<>"","",IF(I31>=70,"N","Y"))) | N31: =IF(I31="","",IF(I31>=70,"",IF(SUM(IF(I31>=70,1,-1)+IF(J31>=70,1,-1))>=0,"Closed","Open"))) | T31: 25 | W31: Hide >> | X31: =IF(COUNTA($F31,$G31)>0,"n/a",IF(H31="","",H31)) | Y31: =IF(COUNTA($F31,$G31)>0,"n/a",IF(I31="","",I31)) | Z31: =IF(COUNTA($F31,$G31)>0,"n/a",IF(J31="","",J31)) | AJ31: << Hide
A32: 6 | C32: 6.3 | D32: Improvement actions are taken to continuously improve performance of the supplier base. Records required. | E32: Supplier performance analysis (e.g. delivery, quality, cost, technology, etc), performance trends, supplier audit reports, Inflation Model, documented goals regarding raw material cost containment | L32: =IF(I32="","",IF(F32<>"","",IF(I32>=70,"N","Y"))) | N32: =IF(I32="","",IF(I32>=70,"",IF(SUM(IF(I32>=70,1,-1)+IF(J32>=70,1,-1))>=0,"Closed","Open"))) | T32: 26 | W32: Hide >> | X32: =IF(COUNTA($F32,$G32)>0,"n/a",IF(H32="","",H32)) | Y32: =IF(COUNTA($F32,$G32)>0,"n/a",IF(I32="","",I32)) | Z32: =IF(COUNTA($F32,$G32)>0,"n/a",IF(J32="","",J32)) | AJ32: << Hide
A33: 7 | C33: 6.4 | D33: A supplier quality assurance system ensures that all purchased product or material conforms to defined specifications and applicable regulatory or customer requirements. Records required. | E33: Receiving inspection, supplier audits, source inspection, qualification testing, Certificate of Compliance (COC), component marking, labeling, etc. | L33: =IF(I33="","",IF(F33<>"","",IF(I33>=70,"N","Y"))) | N33: =IF(I33="","",IF(I33>=70,"",IF(SUM(IF(I33>=70,1,-1)+IF(J33>=70,1,-1))>=0,"Closed","Open"))) | T33: 27 | W33: Hide >> | X33: =IF(COUNTA($F33,$G33)>0,"n/a",IF(H33="","",H33)) | Y33: =IF(COUNTA($F33,$G33)>0,"n/a",IF(I33="","",I33)) | Z33: =IF(COUNTA($F33,$G33)>0,"n/a",IF(J33="","",J33)) | AJ33: << Hide
A34: 8 | C34: 6.5 | D34: A system exists for the identification, verification and protection of customer supplied product that includes notifying the customer if product is damaged or lost. Records required. | E34: Procedures, segregation during storage, limited and controlled access to stored inventories | L34: =IF(I34="","",IF(F34<>"","",IF(I34>=70,"N","Y"))) | N34: =IF(I34="","",IF(I34>=70,"",IF(SUM(IF(I34>=70,1,-1)+IF(J34>=70,1,-1))>=0,"Closed","Open"))) | T34: 28 | W34: Hide >> | X34: =IF(COUNTA($F34,$G34)>0,"n/a",IF(H34="","",H34)) | Y34: =IF(COUNTA($F34,$G34)>0,"n/a",IF(I34="","",I34)) | Z34: =IF(COUNTA($F34,$G34)>0,"n/a",IF(J34="","",J34)) | AJ34: << Hide
A35: 9 | B35: 7.0 INCOMING MATERIAL | C35: 7.1 | D35: Receiving inspection is performed per documented procedures and detailed work instructions. Records required. | E35: Procedures, inspection instructions resources (manpower and equipment) allocated for incoming inspection | L35: =IF(I35="","",IF(F35<>"","",IF(I35>=70,"N","Y"))) | N35: =IF(I35="","",IF(I35>=70,"",IF(SUM(IF(I35>=70,1,-1)+IF(J35>=70,1,-1))>=0,"Closed","Open"))) | T35: 29 | W35: Hide >> | X35: =IF(COUNTA($F35,$G35)>0,"n/a",IF(H35="","",H35)) | Y35: =IF(COUNTA($F35,$G35)>0,"n/a",IF(I35="","",I35)) | Z35: =IF(COUNTA($F35,$G35)>0,"n/a",IF(J35="","",J35)) | AJ35: << Hide
A36: 10 | C36: 7.2 | D36: Inspected material is adequately identified as to acceptance or rejection and traceable to receiving inspection report. Records required. | E36: Quality Control label, marking or use of designated hold area as indicated in the procedure, adherence to FIFO practices | L36: =IF(I36="","",IF(F36<>"","",IF(I36>=70,"N","Y"))) | N36: =IF(I36="","",IF(I36>=70,"",IF(SUM(IF(I36>=70,1,-1)+IF(J36>=70,1,-1))>=0,"Closed","Open"))) | T36: 30 | W36: Hide >> | X36: =IF(COUNTA($F36,$G36)>0,"n/a",IF(H36="","",H36)) | Y36: =IF(COUNTA($F36,$G36)>0,"n/a",IF(I36="","",I36)) | Z36: =IF(COUNTA($F36,$G36)>0,"n/a",IF(J36="","",J36)) | AJ36: << Hide
A37: 11 | C37: 7.3 | D37: Supplier corrective action requests require root cause investigation and records show responses are analyzed. Documented procedures required. Records required. | E37: Availability of written procedure, standardized Corrective Action form, analysis of corrective action cycle time and closure measurements | L37: =IF(I37="","",IF(F37<>"","",IF(I37>=70,"N","Y"))) | N37: =IF(I37="","",IF(I37>=70,"",IF(SUM(IF(I37>=70,1,-1)+IF(J37>=70,1,-1))>=0,"Closed","Open"))) | T37: 31 | W37: Hide >> | X37: =IF(COUNTA($F37,$G37)>0,"n/a",IF(H37="","",H37)) | Y37: =IF(COUNTA($F37,$G37)>0,"n/a",IF(I37="","",I37)) | Z37: =IF(COUNTA($F37,$G37)>0,"n/a",IF(J37="","",J37)) | AJ37: << Hide
A38: 12 | B38: 8.0 MANUFACTURING QUALITY | C38: 8.1 | D38: There is a formal method used to qualify new or rebuilt production equipment prior to production use. | E38: Qualification plan that includes established goals for process yields/up-time, etc. and record of process capability, review and approval, etc. | L38: =IF(I38="","",IF(F38<>"","",IF(I38>=70,"N","Y"))) | N38: =IF(I38="","",IF(I38>=70,"",IF(SUM(IF(I38>=70,1,-1)+IF(J38>=70,1,-1))>=0,"Closed","Open"))) | T38: 32 | W38: Hide >> | X38: =IF(COUNTA($F38,$G38)>0,"n/a",IF(H38="","",H38)) | Y38: =IF(COUNTA($F38,$G38)>0,"n/a",IF(I38="","",I38)) | Z38: =IF(COUNTA($F38,$G38)>0,"n/a",IF(J38="","",J38)) | AJ38: << Hide
A39: 13 | C39: 8.2 | D39: Control Plans are used to plan and deploy inspection and test functions throughout the production process. | E39: Process flow diagram, statistical tools to be used, key inspection points, inspection frequency, records, control responsibility, inspection/test method, gaging used, acceptable yield rates | L39: =IF(I39="","",IF(F39<>"","",IF(I39>=70,"N","Y"))) | N39: =IF(I39="","",IF(I39>=70,"",IF(SUM(IF(I39>=70,1,-1)+IF(J39>=70,1,-1))>=0,"Closed","Open"))) | T39: 33 | W39: Hide >> | X39: =IF(COUNTA($F39,$G39)>0,"n/a",IF(H39="","",H39)) | Y39: =IF(COUNTA($F39,$G39)>0,"n/a",IF(I39="","",I39)) | Z39: =IF(COUNTA($F39,$G39)>0,"n/a",IF(J39="","",J39)) | AJ39: << Hide
A40: 14 | C40: 8.3 | D40: Appropriate work instructions are available where needed that accurately describe all work methods including inspections and tests to be done during production. | E40: Sample size, frequency, method, document control dates/revision level, etc. Handling procedures for Electro-Static Discharge (ESD) | L40: =IF(I40="","",IF(F40<>"","",IF(I40>=70,"N","Y"))) | N40: =IF(I40="","",IF(I40>=70,"",IF(SUM(IF(I40>=70,1,-1)+IF(J40>=70,1,-1))>=0,"Closed","Open"))) | T40: 34 | W40: Hide >> | X40: =IF(COUNTA($F40,$G40)>0,"n/a",IF(H40="","",H40)) | Y40: =IF(COUNTA($F40,$G40)>0,"n/a",IF(I40="","",I40)) | Z40: =IF(COUNTA($F40,$G40)>0,"n/a",IF(J40="","",J40)) | AJ40: << Hide
A41: 15 | C41: 8.4 | D41: Appropriate inspections, tests and process adjustments are made per applicable work instructions to verify conformance at key points throughout the process and prior to shipment. Records required. | E41: Records of inspections performed at incoming, first piece, in-process and/or final inspection or test. Capability study, material test | L41: =IF(I41="","",IF(F41<>"","",IF(I41>=70,"N","Y"))) | N41: =IF(I41="","",IF(I41>=70,"",IF(SUM(IF(I41>=70,1,-1)+IF(J41>=70,1,-1))>=0,"Closed","Open"))) | T41: 35 | W41: Hide >> | X41: =IF(COUNTA($F41,$G41)>0,"n/a",IF(H41="","",H41)) | Y41: =IF(COUNTA($F41,$G41)>0,"n/a",IF(I41="","",I41)) | Z41: =IF(COUNTA($F41,$G41)>0,"n/a",IF(J41="","",J41)) | AJ41: << Hide
A42: 16 | C42: 8.5 | D42: The inspection and process status of product is identified and maintained throughout the production process. Records required. | E42: Batch records, travelers, tags, labels, product markings or use of designated & identified areas. | L42: =IF(I42="","",IF(F42<>"","",IF(I42>=70,"N","Y"))) | N42: =IF(I42="","",IF(I42>=70,"",IF(SUM(IF(I42>=70,1,-1)+IF(J42>=70,1,-1))>=0,"Closed","Open"))) | T42: 36 | W42: Hide >> | X42: =IF(COUNTA($F42,$G42)>0,"n/a",IF(H42="","",H42)) | Y42: =IF(COUNTA($F42,$G42)>0,"n/a",IF(I42="","",I42)) | Z42: =IF(COUNTA($F42,$G42)>0,"n/a",IF(J42="","",J42)) | AJ42: << Hide
A43: 17 | C43: 8.6 | D43: Customers are notified of low yield production lots or issues that affect product reliability. There is a positive recall system to notify customers of nonconforming product that has already been shipped. | E43: Corrective actions, records of customer notifications, reliability test data, etc, documented procedure, records of communication required | L43: =IF(I43="","",IF(F43<>"","",IF(I43>=70,"N","Y"))) | N43: =IF(I43="","",IF(I43>=70,"",IF(SUM(IF(I43>=70,1,-1)+IF(J43>=70,1,-1))>=0,"Closed","Open"))) | T43: 37 | W43: Hide >> | X43: =IF(COUNTA($F43,$G43)>0,"n/a",IF(H43="","",H43)) | Y43: =IF(COUNTA($F43,$G43)>0,"n/a",IF(I43="","",I43)) | Z43: =IF(COUNTA($F43,$G43)>0,"n/a",IF(J43="","",J43)) | AJ43: << Hide
A44: 18 | C44: 8.7 | D44: Key part characteristics and process parameters are reviewed and statistically based controls and/or problem solving tools are used to control variation. | E44: Histograms, run charts, SPC charts, pareto analysis, cause & effect diagrams, DOE, mistake proofing, documented reaction plan & process corrections. | L44: =IF(I44="","",IF(F44<>"","",IF(I44>=70,"N","Y"))) | N44: =IF(I44="","",IF(I44>=70,"",IF(SUM(IF(I44>=70,1,-1)+IF(J44>=70,1,-1))>=0,"Closed","Open"))) | T44: 38 | W44: Hide >> | X44: =IF(COUNTA($F44,$G44)>0,"n/a",IF(H44="","",H44)) | Y44: =IF(COUNTA($F44,$G44)>0,"n/a",IF(I44="","",I44)) | Z44: =IF(COUNTA($F44,$G44)>0,"n/a",IF(J44="","",J44)) | AJ44: << Hide
A45: Bottom | C45: 8.8 | D45: Written improvement plans are implemented to reduce sources of variation. Out of control conditions are noted on charts and documented corrective action is taken to bring the process back into control. Documented procedures required. Records required. | E45: Documented reaction plan & process corrections. SPC trend charts showing current status vs. goals. Improvement plan. Control charts | L45: =IF(I45="","",IF(F45<>"","",IF(I45>=70,"N","Y"))) | N45: =IF(I45="","",IF(I45>=70,"",IF(SUM(IF(I45>=70,1,-1)+IF(J45>=70,1,-1))>=0,"Closed","Open"))) | T45: 39 | W45: Hide >> | X45: =IF(COUNTA($F45,$G45)>0,"n/a",IF(H45="","",H45)) | Y45: =IF(COUNTA($F45,$G45)>0,"n/a",IF(I45="","",I45)) | Z45: =IF(COUNTA($F45,$G45)>0,"n/a",IF(J45="","",J45)) | AJ45: << Hide
A46: 1 | C46: 8.9 | D46: Process capability is measured and actions are taken to maintain established minimum Cpk/Ppk targets. | E46: Documented process capability studies and results (actual vs target Cpk/Ppk) | L46: =IF(I46="","",IF(F46<>"","",IF(I46>=70,"N","Y"))) | N46: =IF(I46="","",IF(I46>=70,"",IF(SUM(IF(I46>=70,1,-1)+IF(J46>=70,1,-1))>=0,"Closed","Open"))) | T46: 40 | W46: Hide >> | X46: =IF(COUNTA($F46,$G46)>0,"n/a",IF(H46="","",H46)) | Y46: =IF(COUNTA($F46,$G46)>0,"n/a",IF(I46="","",I46)) | Z46: =IF(COUNTA($F46,$G46)>0,"n/a",IF(J46="","",J46)) | AJ46: << Hide
A47: 2 | B47: 9.0 NONCONFORMITY CONTROL | C47: 9.1 | D47: Nonconforming materials, parts and assemblies are segregated (where practical) and identified to prevent unapproved use. Documented procedures required. Records required. | E47: Tags, marking, controlled staging areas, etc. | L47: =IF(I47="","",IF(F47<>"","",IF(I47>=70,"N","Y"))) | N47: =IF(I47="","",IF(I47>=70,"",IF(SUM(IF(I47>=70,1,-1)+IF(J47>=70,1,-1))>=0,"Closed","Open"))) | T47: 41 | W47: Hide >> | X47: =IF(COUNTA($F47,$G47)>0,"n/a",IF(H47="","",H47)) | Y47: =IF(COUNTA($F47,$G47)>0,"n/a",IF(I47="","",I47)) | Z47: =IF(COUNTA($F47,$G47)>0,"n/a",IF(J47="","",J47)) | AJ47: << Hide
A48: 3 | C48: 9.2 | D48: Reworked material, parts and assemblies are re-inspected or re-tested to confirm compliance to requirements. Records required. | E48: Inspection record, tag, stamp, etc. | L48: =IF(I48="","",IF(F48<>"","",IF(I48>=70,"N","Y"))) | N48: =IF(I48="","",IF(I48>=70,"",IF(SUM(IF(I48>=70,1,-1)+IF(J48>=70,1,-1))>=0,"Closed","Open"))) | T48: 42 | W48: Hide >> | X48: =IF(COUNTA($F48,$G48)>0,"n/a",IF(H48="","",H48)) | Y48: =IF(COUNTA($F48,$G48)>0,"n/a",IF(I48="","",I48)) | Z48: =IF(COUNTA($F48,$G48)>0,"n/a",IF(J48="","",J48)) | AJ48: << Hide
A49: 4 | C49: 9.3 | D49: Use of nonconforming material is documented under a formal waiver or concession system. Records required. | E49: Written procedure, waiver or concession records | L49: =IF(I49="","",IF(F49<>"","",IF(I49>=70,"N","Y"))) | N49: =IF(I49="","",IF(I49>=70,"",IF(SUM(IF(I49>=70,1,-1)+IF(J49>=70,1,-1))>=0,"Closed","Open"))) | T49: 43 | W49: Hide >> | X49: =IF(COUNTA($F49,$G49)>0,"n/a",IF(H49="","",H49)) | Y49: =IF(COUNTA($F49,$G49)>0,"n/a",IF(I49="","",I49)) | Z49: =IF(COUNTA($F49,$G49)>0,"n/a",IF(J49="","",J49)) | AJ49: << Hide
A50: 5 | C50: 9.4 | D50: Product traceability is maintained (to the extent required by Vertiv) to facilitate problem evaluation and corrective action. Documented procedures required. Records required. | E50: Serial number records, lot number, date of manufacture, labeling and marking of containers or product, etc. | L50: =IF(I50="","",IF(F50<>"","",IF(I50>=70,"N","Y"))) | N50: =IF(I50="","",IF(I50>=70,"",IF(SUM(IF(I50>=70,1,-1)+IF(J50>=70,1,-1))>=0,"Closed","Open"))) | T50: 44 | W50: Hide >> | X50: =IF(COUNTA($F50,$G50)>0,"n/a",IF(H50="","",H50)) | Y50: =IF(COUNTA($F50,$G50)>0,"n/a",IF(I50="","",I50)) | Z50: =IF(COUNTA($F50,$G50)>0,"n/a",IF(J50="","",J50)) | AJ50: << Hide
A51: 6 | B51: 10.0 MEASUREMENT EQUIPMENT | C51: 10.1 | D51: Gage Repeatability & Reproducibility studies are conducted to verify suitability of measuring devices for their use in checking product quality or control of processes. Records required. | E51: GR&R studies, reports | L51: =IF(I51="","",IF(F51<>"","",IF(I51>=70,"N","Y"))) | N51: =IF(I51="","",IF(I51>=70,"",IF(SUM(IF(I51>=70,1,-1)+IF(J51>=70,1,-1))>=0,"Closed","Open"))) | T51: 45 | W51: Hide >> | X51: =IF(COUNTA($F51,$G51)>0,"n/a",IF(H51="","",H51)) | Y51: =IF(COUNTA($F51,$G51)>0,"n/a",IF(I51="","",I51)) | Z51: =IF(COUNTA($F51,$G51)>0,"n/a",IF(J51="","",J51)) | AJ51: << Hide
A52: 7 | C52: 10.2 | D52: Measuring devices, gaging and test equipment are routinely calibrated (traceable to a recognized regulatory body or agency) and controlled per documented procedures. Records required. | E52: Gage calibration stickers, calibration records & procedures, positive identification or segregation of out-of-calibration devices, and inventory, location & status records, etc. | L52: =IF(I52="","",IF(F52<>"","",IF(I52>=70,"N","Y"))) | N52: =IF(I52="","",IF(I52>=70,"",IF(SUM(IF(I52>=70,1,-1)+IF(J52>=70,1,-1))>=0,"Closed","Open"))) | T52: 46 | W52: Hide >> | X52: =IF(COUNTA($F52,$G52)>0,"n/a",IF(H52="","",H52)) | Y52: =IF(COUNTA($F52,$G52)>0,"n/a",IF(I52="","",I52)) | Z52: =IF(COUNTA($F52,$G52)>0,"n/a",IF(J52="","",J52)) | AJ52: << Hide
A53: 8 | C53: 10.3 | D53: Assessments are made to check the validity of previous measurements done on products where out-of-calibration measuring devices were used. Records required. | E53: Assessment records, corrective actions, etc. | L53: =IF(I53="","",IF(F53<>"","",IF(I53>=70,"N","Y"))) | N53: =IF(I53="","",IF(I53>=70,"",IF(SUM(IF(I53>=70,1,-1)+IF(J53>=70,1,-1))>=0,"Closed","Open"))) | T53: 47 | W53: Hide >> | X53: =IF(COUNTA($F53,$G53)>0,"n/a",IF(H53="","",H53)) | Y53: =IF(COUNTA($F53,$G53)>0,"n/a",IF(I53="","",I53)) | Z53: =IF(COUNTA($F53,$G53)>0,"n/a",IF(J53="","",J53)) | AJ53: << Hide
A54: 9 | C54: 10.4 | D54: Appropriate controls are in place to verify the suitability and accuracy of computer software prior to initial use in checking product quality or control of processes. Software is re-verified when revised. Records required. | E54: Verification methods and records, revision levels, distribution/use control, etc. | L54: =IF(I54="","",IF(F54<>"","",IF(I54>=70,"N","Y"))) | N54: =IF(I54="","",IF(I54>=70,"",IF(SUM(IF(I54>=70,1,-1)+IF(J54>=70,1,-1))>=0,"Closed","Open"))) | T54: 48 | W54: Hide >> | X54: =IF(COUNTA($F54,$G54)>0,"n/a",IF(H54="","",H54)) | Y54: =IF(COUNTA($F54,$G54)>0,"n/a",IF(I54="","",I54)) | Z54: =IF(COUNTA($F54,$G54)>0,"n/a",IF(J54="","",J54)) | AJ54: << Hide
A55: 10 | B55: 11.0 PREVENTIVE MAINTENANCE | C55: 11.1 | D55: Tools are stored in an appropriate, clearly defined area, with systematic tracking that provide traceability, particularly of customer-owned tools and equipment. Records required. | E55: Review of storage area, labeling, tooling records | L55: =IF(I55="","",IF(F55<>"","",IF(I55>=70,"N","Y"))) | N55: =IF(I55="","",IF(I55>=70,"",IF(SUM(IF(I55>=70,1,-1)+IF(J55>=70,1,-1))>=0,"Closed","Open"))) | T55: 49 | W55: Hide >> | X55: =IF(COUNTA($F55,$G55)>0,"n/a",IF(H55="","",H55)) | Y55: =IF(COUNTA($F55,$G55)>0,"n/a",IF(I55="","",I55)) | Z55: =IF(COUNTA($F55,$G55)>0,"n/a",IF(J55="","",J55)) | AJ55: << Hide
A56: 11 | C56: 11.2 | D56: A formal Preventive Maintenance system exists for production equipment, tools and fixtures. | E56: Review of system, PM plans, PM schedule and compliance results | L56: =IF(I56="","",IF(F56<>"","",IF(I56>=70,"N","Y"))) | N56: =IF(I56="","",IF(I56>=70,"",IF(SUM(IF(I56>=70,1,-1)+IF(J56>=70,1,-1))>=0,"Closed","Open"))) | T56: 50 | W56: Hide >> | X56: =IF(COUNTA($F56,$G56)>0,"n/a",IF(H56="","",H56)) | Y56: =IF(COUNTA($F56,$G56)>0,"n/a",IF(I56="","",I56)) | Z56: =IF(COUNTA($F56,$G56)>0,"n/a",IF(J56="","",J56)) | AJ56: << Hide
A57: 12 | C57: 11.3 | D57: Preventive Maintenance schedule is followed. Product cannot be made with tools that are outside of maintenance period. Performance is audited. | E57: No equipment, tools, or fixtures are in use that are outside TPM schedule, or have unclear status | L57: =IF(I57="","",IF(F57<>"","",IF(I57>=70,"N","Y"))) | N57: =IF(I57="","",IF(I57>=70,"",IF(SUM(IF(I57>=70,1,-1)+IF(J57>=70,1,-1))>=0,"Closed","Open"))) | T57: 51 | W57: Hide >> | X57: =IF(COUNTA($F57,$G57)>0,"n/a",IF(H57="","",H57)) | Y57: =IF(COUNTA($F57,$G57)>0,"n/a",IF(I57="","",I57)) | Z57: =IF(COUNTA($F57,$G57)>0,"n/a",IF(J57="","",J57)) | AJ57: << Hide
A58: 13 | B58: 12.0 STORAGE & PACKAGING | C58: 12.1 | D58: Areas around the facility are clean and orderly. Tools and equipment are properly stored and readily available for use. Lighting and air quality are adequate. | E58: Observe production, office & product storage areas for use of 5S/6S principles (Sort, Set-in-order, Shine, Standardize, Sustain + Safety) | L58: =IF(I58="","",IF(F58<>"","",IF(I58>=70,"N","Y"))) | N58: =IF(I58="","",IF(I58>=70,"",IF(SUM(IF(I58>=70,1,-1)+IF(J58>=70,1,-1))>=0,"Closed","Open"))) | T58: 52 | W58: Hide >> | X58: =IF(COUNTA($F58,$G58)>0,"n/a",IF(H58="","",H58)) | Y58: =IF(COUNTA($F58,$G58)>0,"n/a",IF(I58="","",I58)) | Z58: =IF(COUNTA($F58,$G58)>0,"n/a",IF(J58="","",J58)) | AJ58: << Hide
A59: 14 | C59: 12.2 | D59: Proper equipment and methods are used to prevent product damage or loss in all phases of the material handling process. | E59: Observe handling and transit of raw material, work-in-process, and finished goods. | L59: =IF(I59="","",IF(F59<>"","",IF(I59>=70,"N","Y"))) | N59: =IF(I59="","",IF(I59>=70,"",IF(SUM(IF(I59>=70,1,-1)+IF(J59>=70,1,-1))>=0,"Closed","Open"))) | T59: 53 | W59: Hide >> | X59: =IF(COUNTA($F59,$G59)>0,"n/a",IF(H59="","",H59)) | Y59: =IF(COUNTA($F59,$G59)>0,"n/a",IF(I59="","",I59)) | Z59: =IF(COUNTA($F59,$G59)>0,"n/a",IF(J59="","",J59)) | AJ59: << Hide
A60: 15 | C60: 12.3 | D60: Documented procedures / evidence are followed to ensure proper control and preservation of handling, storage (FIFO), packaging, and delivery of product. | E60: FIFO practices are defined, packaging specifications, test results, handling and storage procedures. | L60: =IF(I60="","",IF(F60<>"","",IF(I60>=70,"N","Y"))) | N60: =IF(I60="","",IF(I60>=70,"",IF(SUM(IF(I60>=70,1,-1)+IF(J60>=70,1,-1))>=0,"Closed","Open"))) | T60: 54 | W60: Hide >> | X60: =IF(COUNTA($F60,$G60)>0,"n/a",IF(H60="","",H60)) | Y60: =IF(COUNTA($F60,$G60)>0,"n/a",IF(I60="","",I60)) | Z60: =IF(COUNTA($F60,$G60)>0,"n/a",IF(J60="","",J60)) | AJ60: << Hide
A61: 16 | C61: 12.4 | D61: Suitability of product packaging is reviewed and any concerns are communicated to the customer prior to initial production shipment. Packaging tests if required. Records required. | E61: Technical review, packaging / shipping tests, packaging work instructions, carton strength tests | L61: =IF(I61="","",IF(F61<>"","",IF(I61>=70,"N","Y"))) | N61: =IF(I61="","",IF(I61>=70,"",IF(SUM(IF(I61>=70,1,-1)+IF(J61>=70,1,-1))>=0,"Closed","Open"))) | T61: 55 | W61: Hide >> | X61: =IF(COUNTA($F61,$G61)>0,"n/a",IF(H61="","",H61)) | Y61: =IF(COUNTA($F61,$G61)>0,"n/a",IF(I61="","",I61)) | Z61: =IF(COUNTA($F61,$G61)>0,"n/a",IF(J61="","",J61)) | AJ61: << Hide
A62: 17 | C62: 12.5 | D62: Stored product / material is periodically inspected, and where applicable, actions are taken to prevent deterioration per documented procedures. | E62: Doc'd list of shelf-life sensitive products / materials (e.g., sealants, adhesives, solder paste, paint/varnish, o'rings). Look for poor storage conditions & damage (e.g., rust or water damage). Handling procedures for Electro-Static Discharge (ESD) & other sensitive conditions. | L62: =IF(I62="","",IF(F62<>"","",IF(I62>=70,"N","Y"))) | N62: =IF(I62="","",IF(I62>=70,"",IF(SUM(IF(I62>=70,1,-1)+IF(J62>=70,1,-1))>=0,"Closed","Open"))) | T62: 56 | W62: Hide >> | X62: =IF(COUNTA($F62,$G62)>0,"n/a",IF(H62="","",H62)) | Y62: =IF(COUNTA($F62,$G62)>0,"n/a",IF(I62="","",I62)) | Z62: =IF(COUNTA($F62,$G62)>0,"n/a",IF(J62="","",J62)) | AJ62: << Hide
A63: 18 | B63: 13.0 ENVIRONMENTAL | C63: 13.1 | D63: A documented environmental policy exists that includes a commitment to comply with relevant environmental legislation and regulations and to continual improvement and pollution prevention. | E63: Environmental policy statement document | L63: =IF(I63="","",IF(F63<>"","",IF(I63>=70,"N","Y"))) | N63: =IF(I63="","",IF(I63>=70,"",IF(SUM(IF(I63>=70,1,-1)+IF(J63>=70,1,-1))>=0,"Closed","Open"))) | T63: 57 | W63: Hide >> | X63: =IF(COUNTA($F63,$G63)>0,"n/a",IF(H63="","",H63)) | Y63: =IF(COUNTA($F63,$G63)>0,"n/a",IF(I63="","",I63)) | Z63: =IF(COUNTA($F63,$G63)>0,"n/a",IF(J63="","",J63)) | AJ63: << Hide
A64: Bottom | C64: 13.2 | D64: There is an environmental management system that ensures compliance to all applicable government regulations and there are no outstanding, unresolved violations of these regulations. | E64: Records of agency/gov inspection or certification, doc'd procedures for measuring and monitoring environmentally sensitive activities w/ list of mtl's and areas where used, tracking of hazardous mtl's or waste. | L64: =IF(I64="","",IF(F64<>"","",IF(I64>=70,"N","Y"))) | N64: =IF(I64="","",IF(I64>=70,"",IF(SUM(IF(I64>=70,1,-1)+IF(J64>=70,1,-1))>=0,"Closed","Open"))) | T64: 58 | W64: Hide >> | X64: =IF(COUNTA($F64,$G64)>0,"n/a",IF(H64="","",H64)) | Y64: =IF(COUNTA($F64,$G64)>0,"n/a",IF(I64="","",I64)) | Z64: =IF(COUNTA($F64,$G64)>0,"n/a",IF(J64="","",J64)) | AJ64: << Hide
A65: 1 | C65: 13.3 | D65: A system is in place to minimize the use, disposal and emissions of hazardous chemicals and to ensure that Class I ozone depleting chemicals are not used in the manufacturing process. | E65: Record of purchases, waste stream and consumption; inventory control procedures. | L65: =IF(I65="","",IF(F65<>"","",IF(I65>=70,"N","Y"))) | N65: =IF(I65="","",IF(I65>=70,"",IF(SUM(IF(I65>=70,1,-1)+IF(J65>=70,1,-1))>=0,"Closed","Open"))) | T65: 59 | W65: Hide >> | X65: =IF(COUNTA($F65,$G65)>0,"n/a",IF(H65="","",H65)) | Y65: =IF(COUNTA($F65,$G65)>0,"n/a",IF(I65="","",I65)) | Z65: =IF(COUNTA($F65,$G65)>0,"n/a",IF(J65="","",J65)) | AJ65: << Hide
A66: 2 | C66: 13.4 | D66: An on-going emphasis is placed on using materials that are; compliant with applicable regulations like RoHS & WEEE, biodegradable, recyclable, re-usable, reduces pollutant emissions at the point of use. | E66: Records / use of non-hazardous (RoHS/WEEE compliant) materials in production, biodegradable materials, returnable containers or packaging, recycling program, packaging materials made of recycled materials. | L66: =IF(I66="","",IF(F66<>"","",IF(I66>=70,"N","Y"))) | N66: =IF(I66="","",IF(I66>=70,"",IF(SUM(IF(I66>=70,1,-1)+IF(J66>=70,1,-1))>=0,"Closed","Open"))) | T66: 60 | W66: Hide >> | X66: =IF(COUNTA($F66,$G66)>0,"n/a",IF(H66="","",H66)) | Y66: =IF(COUNTA($F66,$G66)>0,"n/a",IF(I66="","",I66)) | Z66: =IF(COUNTA($F66,$G66)>0,"n/a",IF(J66="","",J66)) | AJ66: << Hide
A67: 3 | B67: 14.0 OCCUPATIONAL HEALTH & SAFETY | C67: 14.1 | D67: The Occupation Health & Safety (OHS) management system addresses the safety of personnel without comprising the achievement of product quality requirements. | E67: Procedure for OHS training, communications, emergency preparedness and response, monitoring and performance measurements | L67: =IF(I67="","",IF(F67<>"","",IF(I67>=70,"N","Y"))) | N67: =IF(I67="","",IF(I67>=70,"",IF(SUM(IF(I67>=70,1,-1)+IF(J67>=70,1,-1))>=0,"Closed","Open"))) | T67: 61 | W67: Hide >> | X67: =IF(COUNTA($F67,$G67)>0,"n/a",IF(H67="","",H67)) | Y67: =IF(COUNTA($F67,$G67)>0,"n/a",IF(I67="","",I67)) | Z67: =IF(COUNTA($F67,$G67)>0,"n/a",IF(J67="","",J67)) | AJ67: << Hide
A68: 4 | C68: 14.2 | D68: The Occupation Health & Safety (OHS) policy states the organization’s health and safety objectives and management's commitment to continual improvement of OHS metrics. | E68: Policies and procedures, health & safety trend charts, accident rate improvement history, etc. | L68: =IF(I68="","",IF(F68<>"","",IF(I68>=70,"N","Y"))) | N68: =IF(I68="","",IF(I68>=70,"",IF(SUM(IF(I68>=70,1,-1)+IF(J68>=70,1,-1))>=0,"Closed","Open"))) | T68: 62 | W68: Hide >> | X68: =IF(COUNTA($F68,$G68)>0,"n/a",IF(H68="","",H68)) | Y68: =IF(COUNTA($F68,$G68)>0,"n/a",IF(I68="","",I68)) | Z68: =IF(COUNTA($F68,$G68)>0,"n/a",IF(J68="","",J68)) | AJ68: << Hide
A69: 5 | C69: 14.3 | D69: Procedures are used for the on-going identification of hazards, the assessment of risks, and the implementation of necessary control measures. | E69: Safety committee or group meeting minutes, accident investigation reports, safety audit reports | L69: =IF(I69="","",IF(F69<>"","",IF(I69>=70,"N","Y"))) | N69: =IF(I69="","",IF(I69>=70,"",IF(SUM(IF(I69>=70,1,-1)+IF(J69>=70,1,-1))>=0,"Closed","Open"))) | T69: 63 | W69: Hide >> | X69: =IF(COUNTA($F69,$G69)>0,"n/a",IF(H69="","",H69)) | Y69: =IF(COUNTA($F69,$G69)>0,"n/a",IF(I69="","",I69)) | Z69: =IF(COUNTA($F69,$G69)>0,"n/a",IF(J69="","",J69)) | AJ69: << Hide
A70: 6 | B70: 15.0 CORPORATE COMPLIANCE (ROHS) | C70: 15.1 | D70: A RoHS compliance policy is documented and maintained that defines personnel responsibilities, requirements for material and process qualification, on-going compliance verification, manufacturing controls, declaration of compliance and records. | E70: Documented procedures that set requirements for planning, verification, on-going control, record keeping & customer communications. Record the names and titles of the responsible personnel. | L70: =IF(I70="","",IF(F70<>"","",IF(I70>=70,"N","Y"))) | N70: =IF(I70="","",IF(I70>=70,"",IF(SUM(IF(I70>=70,1,-1)+IF(J70>=70,1,-1))>=0,"Closed","Open"))) | T70: 64 | W70: Hide >> | X70: =IF(COUNTA($F70,$G70)>0,"n/a",IF(H70="","",H70)) | Y70: =IF(COUNTA($F70,$G70)>0,"n/a",IF(I70="","",I70)) | Z70: =IF(COUNTA($F70,$G70)>0,"n/a",IF(J70="","",J70)) | AJ70: << Hide
A71: 7 | C71: 15.2 | D71: Test methods are established for each RoHS controlled hazardous substance. Test sampling plan is based on analysis of risk for each commodity and/or manufacturing process used. | E71: Assessment of risk by part-type or manufacturing process used. Procedures, test methods, sampling plan, control plan. | L71: =IF(I71="","",IF(F71<>"","",IF(I71>=70,"N","Y"))) | N71: =IF(I71="","",IF(I71>=70,"",IF(SUM(IF(I71>=70,1,-1)+IF(J71>=70,1,-1))>=0,"Closed","Open"))) | T71: 65 | W71: Hide >> | X71: =IF(COUNTA($F71,$G71)>0,"n/a",IF(H71="","",H71)) | Y71: =IF(COUNTA($F71,$G71)>0,"n/a",IF(I71="","",I71)) | Z71: =IF(COUNTA($F71,$G71)>0,"n/a",IF(J71="","",J71)) | AJ71: << Hide
A72: 8 | C72: 15.3 | D72: RoHS technical requirements and inspection criteria are documented and available where needed, e.g. solder fillet, tin whiskers. | E72: Test methods/procedures, tin whisker analysis instructions, XRF work instructions, QC audits, etc. Ref to Jedec/IPC Joint publication JP-002. | L72: =IF(I72="","",IF(F72<>"","",IF(I72>=70,"N","Y"))) | N72: =IF(I72="","",IF(I72>=70,"",IF(SUM(IF(I72>=70,1,-1)+IF(J72>=70,1,-1))>=0,"Closed","Open"))) | T72: 66 | W72: Hide >> | X72: =IF(COUNTA($F72,$G72)>0,"n/a",IF(H72="","",H72)) | Y72: =IF(COUNTA($F72,$G72)>0,"n/a",IF(I72="","",I72)) | Z72: =IF(COUNTA($F72,$G72)>0,"n/a",IF(J72="","",J72)) | AJ72: << Hide
A73: 9 | C73: 15.4 | D73: Test methods and acceptance limits follow recognized standards and RoHS requirements. | E73: Acceptance limits do not exceed RoHS limits. References to recognized standard test protocols, such as, ISO, IEC, EPA. | L73: =IF(I73="","",IF(F73<>"","",IF(I73>=70,"N","Y"))) | N73: =IF(I73="","",IF(I73>=70,"",IF(SUM(IF(I73>=70,1,-1)+IF(J73>=70,1,-1))>=0,"Closed","Open"))) | T73: 67 | W73: Hide >> | X73: =IF(COUNTA($F73,$G73)>0,"n/a",IF(H73="","",H73)) | Y73: =IF(COUNTA($F73,$G73)>0,"n/a",IF(I73="","",I73)) | Z73: =IF(COUNTA($F73,$G73)>0,"n/a",IF(J73="","",J73)) | AJ73: << Hide
A74: 10 | C74: 15.5 | D74: Incoming materials and finished goods are periodically tested with appropriate equipment to confirm RoHS compliance. Compliance declarations and test records are maintained for a minimum of 5 years. | E74: RoHS testing procedure, sampling plan/frequency, test records. Use of XRF analyzer, atomic absorption analyzer, UV-VIS equipment, etc.. Qualified independent chemical lab w/A2LA accreditation or equivalent. | L74: =IF(I74="","",IF(F74<>"","",IF(I74>=70,"N","Y"))) | N74: =IF(I74="","",IF(I74>=70,"",IF(SUM(IF(I74>=70,1,-1)+IF(J74>=70,1,-1))>=0,"Closed","Open"))) | T74: 68 | W74: Hide >> | X74: =IF(COUNTA($F74,$G74)>0,"n/a",IF(H74="","",H74)) | Y74: =IF(COUNTA($F74,$G74)>0,"n/a",IF(I74="","",I74)) | Z74: =IF(COUNTA($F74,$G74)>0,"n/a",IF(J74="","",J74)) | AJ74: << Hide
A75: 11 | B75: 16.0 CORPORATE COMPLIANCE (REACH) | C75: 16.1 | D75: REACH compliance policy is documented and maintained that defines the requirements for REACH compliance and on-going verification. | E75: Policy statement or procedure. | L75: =IF(I75="","",IF(F75<>"","",IF(I75>=70,"N","Y"))) | N75: =IF(I75="","",IF(I75>=70,"",IF(SUM(IF(I75>=70,1,-1)+IF(J75>=70,1,-1))>=0,"Closed","Open"))) | T75: 69 | W75: Hide >> | X75: =IF(COUNTA($F75,$G75)>0,"n/a",IF(H75="","",H75)) | Y75: =IF(COUNTA($F75,$G75)>0,"n/a",IF(I75="","",I75)) | Z75: =IF(COUNTA($F75,$G75)>0,"n/a",IF(J75="","",J75)) | AJ75: << Hide
A76: 12 | C76: 16.2 | D76: Responsibilities for REACH have been clearly defined and assigned to appropriate personnel. | E76: Look for identification of an individual or individuals (i.e.., naming an entire department is not acceptable). Record the names and titles of the responsible individuals. | L76: =IF(I76="","",IF(F76<>"","",IF(I76>=70,"N","Y"))) | N76: =IF(I76="","",IF(I76>=70,"",IF(SUM(IF(I76>=70,1,-1)+IF(J76>=70,1,-1))>=0,"Closed","Open"))) | T76: 70 | W76: Hide >> | X76: =IF(COUNTA($F76,$G76)>0,"n/a",IF(H76="","",H76)) | Y76: =IF(COUNTA($F76,$G76)>0,"n/a",IF(I76="","",I76)) | Z76: =IF(COUNTA($F76,$G76)>0,"n/a",IF(J76="","",J76)) | AJ76: << Hide
A77: 13 | C77: 16.3 | D77: REACH Compliance Documents and instructions for their use are established and followed. | E77: Compliance Plan, Supplier Letters, Customer Letters | L77: =IF(I77="","",IF(F77<>"","",IF(I77>=70,"N","Y"))) | N77: =IF(I77="","",IF(I77>=70,"",IF(SUM(IF(I77>=70,1,-1)+IF(J77>=70,1,-1))>=0,"Closed","Open"))) | T77: 71 | W77: Hide >> | X77: =IF(COUNTA($F77,$G77)>0,"n/a",IF(H77="","",H77)) | Y77: =IF(COUNTA($F77,$G77)>0,"n/a",IF(I77="","",I77)) | Z77: =IF(COUNTA($F77,$G77)>0,"n/a",IF(J77="","",J77)) | AJ77: << Hide
A78: 14 | C78: 16.4 | D78: Supplier must have a system in place to communicate safe handling information (such as a Material Safety Data Sheet) for any dangerous substances contained in or on it's products. | E78: Database/files. Records of communication to customers of the Material Safety Data Sheet (MSDS) or Safety Data Sheet (SDS) in the EU which may include Exposure Scenario (ES) and/or Risk Management Measures (RMM). | L78: =IF(I78="","",IF(F78<>"","",IF(I78>=70,"N","Y"))) | N78: =IF(I78="","",IF(I78>=70,"",IF(SUM(IF(I78>=70,1,-1)+IF(J78>=70,1,-1))>=0,"Closed","Open"))) | T78: 72 | W78: Hide >> | X78: =IF(COUNTA($F78,$G78)>0,"n/a",IF(H78="","",H78)) | Y78: =IF(COUNTA($F78,$G78)>0,"n/a",IF(I78="","",I78)) | Z78: =IF(COUNTA($F78,$G78)>0,"n/a",IF(J78="","",J78)) | AJ78: << Hide
A79: 15 | C79: 16.5 | D79: The supplier has informed Vertiv if they are providing (or will be providing) Vertiv with products that contain Substances of Very High Concern (SVHC) that exceed 0.1% wt./wt. | E79: If the official candidate list has been published by the ECHA (European Chemicals Agency), then look for records of communication to Vertiv of the presence of SVHC, if applicable. Traceability of chemical identification. | L79: =IF(I79="","",IF(F79<>"","",IF(I79>=70,"N","Y"))) | N79: =IF(I79="","",IF(I79>=70,"",IF(SUM(IF(I79>=70,1,-1)+IF(J79>=70,1,-1))>=0,"Closed","Open"))) | T79: 73 | W79: Hide >> | X79: =IF(COUNTA($F79,$G79)>0,"n/a",IF(H79="","",H79)) | Y79: =IF(COUNTA($F79,$G79)>0,"n/a",IF(I79="","",I79)) | Z79: =IF(COUNTA($F79,$G79)>0,"n/a",IF(J79="","",J79)) | AJ79: << Hide
A80: 16 | B80: 17.0 CORPORATE COMPLIANCE (CONFLICT MINERALS) | C80: 17.1 | D80: Supplier has a procedure in place to identify the presence of tin, tungsten, tantalum and gold (3TG) in supplied products. | E80: Supplier will provide the valid procedure with steps of identifying 3TG in products. | L80: =IF(I80="","",IF(F80<>"","",IF(I80>=70,"N","Y"))) | N80: =IF(I80="","",IF(I80>=70,"",IF(SUM(IF(I80>=70,1,-1)+IF(J80>=70,1,-1))>=0,"Closed","Open"))) | T80: 74 | W80: Hide >> | X80: =IF(COUNTA($F80,$G80)>0,"n/a",IF(H80="","",H80)) | Y80: =IF(COUNTA($F80,$G80)>0,"n/a",IF(I80="","",I80)) | Z80: =IF(COUNTA($F80,$G80)>0,"n/a",IF(J80="","",J80)) | AJ80: << Hide
A81: 17 | C81: 17.2 | D81: If products contain 3TG, Supplier has a published CM policy or statement and an annual Conflict Minerals Reporting Template (CMRT) data collection program in place. | E81: Supplier will provide the CM policy or statement and company level CMRT with an effective date applicable to the current year. | L81: =IF(I81="","",IF(F81<>"","",IF(I81>=70,"N","Y"))) | N81: =IF(I81="","",IF(I81>=70,"",IF(SUM(IF(I81>=70,1,-1)+IF(J81>=70,1,-1))>=0,"Closed","Open"))) | T81: 75 | W81: Hide >> | X81: =IF(COUNTA($F81,$G81)>0,"n/a",IF(H81="","",H81)) | Y81: =IF(COUNTA($F81,$G81)>0,"n/a",IF(I81="","",I81)) | Z81: =IF(COUNTA($F81,$G81)>0,"n/a",IF(J81="","",J81)) | AJ81: << Hide
A82: 18 | C82: 17.3 | D82: Supplier provided the current year CMRT to Vertiv via Assent Compliance Tool. | E82: Supplier will provide its Assent account with submitted CMRT status or look for other records of the submitted valid CMRT to Vertiv. | L82: =IF(I82="","",IF(F82<>"","",IF(I82>=70,"N","Y"))) | N82: =IF(I82="","",IF(I82>=70,"",IF(SUM(IF(I82>=70,1,-1)+IF(J82>=70,1,-1))>=0,"Closed","Open"))) | T82: 76 | W82: Hide >> | X82: =IF(COUNTA($F82,$G82)>0,"n/a",IF(H82="","",H82)) | Y82: =IF(COUNTA($F82,$G82)>0,"n/a",IF(I82="","",I82)) | Z82: =IF(COUNTA($F82,$G82)>0,"n/a",IF(J82="","",J82)) | AJ82: << Hide
A83: Bottom | B83: 18.0 CORPORATE COMPLIANCE (CODE OF CONDUCT) | C83: 18.1 | D83: Supplier maintains a code of conduct or a policy that addresses general ethical issues and responsibility, and maintains a process for employees to report concerns | E83: Supplier should provide the code of conduct or policy to Vertiv for review. The supplier's legal or compliance department would likely be the correct contact. | L83: =IF(I83="","",IF(F83<>"","",IF(I83>=70,"N","Y"))) | N83: =IF(I83="","",IF(I83>=70,"",IF(SUM(IF(I83>=70,1,-1)+IF(J83>=70,1,-1))>=0,"Closed","Open"))) | T83: 77 | W83: Hide >> | X83: =IF(COUNTA($F83,$G83)>0,"n/a",IF(H83="","",H83)) | Y83: =IF(COUNTA($F83,$G83)>0,"n/a",IF(I83="","",I83)) | Z83: =IF(COUNTA($F83,$G83)>0,"n/a",IF(J83="","",J83)) | AJ83: << Hide
A84: 1 | C84: 18.2 | D84: Supplier must agree to comply with the Vertiv Supplier Code of Conduct. | E84: Supplier will acknowledge and agree to comply with the Vertiv Supplier Code of Conduct via Vertiv's annual conflict minerals and supplier outreach program. | L84: =IF(I84="","",IF(F84<>"","",IF(I84>=70,"N","Y"))) | M84: =IF(H84="","",IF(H84>=70,"",IF(SUM(IF(H84>=70,1,-1)+IF(I84>=70,1,-1))>=0,"Closed","Open"))) | N84: =IF(I84="","",IF(I84>=70,"",IF(SUM(IF(I84>=70,1,-1)+IF(J84>=70,1,-1))>=0,"Closed","Open"))) | T84: 78 | W84: Hide >> | X84: =IF(COUNTA($F84,$G84)>0,"n/a",IF(H84="","",H84)) | Y84: =IF(COUNTA($F84,$G84)>0,"n/a",IF(I84="","",I84)) | Z84: =IF(COUNTA($F84,$G84)>0,"n/a",IF(J84="","",J84)) | AJ84: << Hide
A85: 2 | C85: 18.3 | D85: Supplier maintains a human rights policy that addresses child labor, forced labor, human trafficking, working hour and wage laws, and non-discrimination. | E85: Supplier should provide the policy to Vertiv for review. The supplier's legal or compliance department would likely be the correct contact. | L85: =IF(I85="","",IF(F85<>"","",IF(I85>=70,"N","Y"))) | M85: =IF(H85="","",IF(H85>=70,"",IF(SUM(IF(H85>=70,1,-1)+IF(I85>=70,1,-1))>=0,"Closed","Open"))) | N85: =IF(I85="","",IF(I85>=70,"",IF(SUM(IF(I85>=70,1,-1)+IF(J85>=70,1,-1))>=0,"Closed","Open"))) | T85: 79 | W85: Hide >> | X85: =IF(COUNTA($F85,$G85)>0,"n/a",IF(H85="","",H85)) | Y85: =IF(COUNTA($F85,$G85)>0,"n/a",IF(I85="","",I85)) | Z85: =IF(COUNTA($F85,$G85)>0,"n/a",IF(J85="","",J85)) | AJ85: << Hide
A86: 3 | C86: 18.4 | D86: Supplier prohibs corruption, including bribes, kickbacks, or other improper payments, with binding rules for all employees. | E86: Supplier should provide the program documents to Vertiv for review. The supplier's legal or compliance department would likely be the correct contact. | L86: =IF(I86="","",IF(F86<>"","",IF(I86>=70,"N","Y"))) | M86: =IF(H86="","",IF(H86>=70,"",IF(SUM(IF(H86>=70,1,-1)+IF(I86>=70,1,-1))>=0,"Closed","Open"))) | N86: =IF(I86="","",IF(I86>=70,"",IF(SUM(IF(I86>=70,1,-1)+IF(J86>=70,1,-1))>=0,"Closed","Open"))) | T86: 80 | W86: Hide >> | X86: =IF(COUNTA($F86,$G86)>0,"n/a",IF(H86="","",H86)) | Y86: =IF(COUNTA($F86,$G86)>0,"n/a",IF(I86="","",I86)) | Z86: =IF(COUNTA($F86,$G86)>0,"n/a",IF(J86="","",J86)) | AJ86: << Hide
E88: TOTAL SCORES FOR THIS CHECKLIST ONLY | F88: Not Applicable | G88: Not Verified | H88: Supplier Self-Audit Std Chklst SCORE | I88: On-Site Audit Std Chklst SCORE | J88: After CAPA Verif. Std Chklst SCORE | K88: On-Site Audit Findings | R88: Supplier Corrective & Preventive Action Plan
H89: =SUM($X$7:$X$86) -> 0 | I89: =SUM($Y$7:$Y$86) -> 0 | J89: =SUM($Z$7:$Z$86) -> 0 | K89: Corrective Action plans will be submitted on (date): | R89: Submitted by (name & title):
F90: =COUNTA(F7:F86) -> 0 | G90: =COUNTA(G7:G86) -> 0 | H90: =(COUNTA($D$7:$D$86)-($F90+$G90))*100 -> 8000 | I90: =(COUNTA($D$7:$D$86)-($F90+$G90))*100 -> 8000 | J90: =(COUNTA($D$7:$D$86)-($F90+$G90))*100 -> 8000 | K90: Vertiv Audit Leader (name & title):
E91: Final Standard Checklist Score | H91: =(H89/H90) -> 0 | I91: =(I89/I90) -> 0 | J91: =(J89/J90) -> 0 | K91: Supplier QA Representative (name & title):
E92: Date: | F92: =IF('Supplier Profile & Audit Plan'!$A$46="","",'Supplier Profile & Audit Plan'!$A$46) | K92: CA-PA Verification & Finding Closure Date: | R92: Date Supplier CA-PA Plan Reviewed:
D94: SCORING GUIDELINES | H94: Top | S94: Top
D95: Supplier to use scoring instructions below when assigning Supplier Self-Audit Score.
D96: Scoring Instructions for Supplier Self-Audit
D97: Based on knowledge of your quality system, select score that best describes level of compliance to the Requirement. If Requirement does not apply, place "x" in the "Not Applicable" column. Note that some Requirements are mandatory.
D98: 0 = REQUIREMENT NOT ADDRESSED
D99: 40 = RARELY COMPLIES; Corrective actions planned or in-progress
D100: 60 = SOME NON-COMPLIANCES; Corrective actions planned or in-progress
D101: 70 = NO NON-COMPLIANCES; Meets Minimum Requirement / No CA required
D102: 80 = NO NON-COMPLIANCES; Exceeds Minimum Requirement / No CA required
...

Sheet Audit Results
A1: Note: The Audit Results page fills in automatically with the exception of a few fields near the bottom of the page. | L1: VSAC-Report-Template-2021 V1c | Z1: Hide >>> | AA1: =Checklist!U92 -> 0 | AD1: <<< Hide
B2: Vertiv Supplier Audit Checklist | G2: Supplier: | H2: =IF('Supplier Profile & Audit Plan'!$A$6="","",'Supplier Profile & Audit Plan'!$A$6) -> Savannah Tank & Equipment Corp.
C3: Audit Results | G3: Commodity: | H3: =IF('Supplier Profile & Audit Plan'!A49="","",'Supplier Profile & Audit Plan'!A49) -> Sheet Metal & Enclosure
G4: =IF('Supplier Profile & Audit Plan'!A46="","",'Supplier Profile & Audit Plan'!A46) | L4: Section Scores
A5: Vertiv Region: | C5: =IF('Supplier Profile & Audit Plan'!$A$45="","",'Supplier Profile & Audit Plan'!$A$45) -> AMER | G5: Supplier Self-Audit SCORE | H5: On-Site Audit SCORE | I5: CA Req'd? (Y) | J5: CA Status (Open) | K5: After CA Verif. SCORE | L5: Supplier Self-Audit SCORE | M5: On-Site Audit SCORE | N5: After CA Verif. SCORE
A6: Standard Checklist Section | C6: Total Req'mnts | D6: Mandatory Req'mnts | E6: Req. No.
AA7: Audit Team Recommendation | AB7: Final Disposition
A8: 1 | B8: Quality Management | C8: 6 | D8: 3 | E8: M | F8: 1.1 | G8: =Checklist!X7 | H8: =Checklist!Y7 | I8: =Checklist!L7 | J8: =IF(H8="","",IF(Checklist!N7="","",Checklist!N7)) | K8: =Checklist!Z7 | L8: =IF(SUM(G8:G13)=0,"0",SUM(G8:G13)/($C8-(COUNTIF(G8:G13,"n/a")))) -> 0 | M8: =IF(SUM(H8:H13)=0,"0",SUM(H8:H13)/($C8-(COUNTIF(H8:H13,"n/a")))) -> 0 | N8: =IF(SUM(K8:K13)=0,"0",SUM(K8:K13)/($C8-(COUNTIF(K8:K13,"n/a")))) -> 0 | AA8: Passed | AB8: Approved
E9: M | F9: 1.2 | G9: =Checklist!X8 | H9: =Checklist!Y8 | I9: =Checklist!L8 | J9: =IF(H9="","",IF(Checklist!N8="","",Checklist!N8)) | K9: =Checklist!Z8 | AA9: Conditional Approval | AB9: Conditionally Approved
F10: 1.3 | G10: =Checklist!X9 | H10: =Checklist!Y9 | I10: =Checklist!L9 | J10: =IF(H10="","",IF(Checklist!N9="","",Checklist!N9)) | K10: =Checklist!Z9 | AA10: Rejected | AB10: Not Approved
F11: 1.4 | G11: =Checklist!X10 | H11: =Checklist!Y10 | I11: =Checklist!L10 | J11: =IF(H11="","",IF(Checklist!N10="","",Checklist!N10)) | K11: =Checklist!Z10
E12: M | F12: 1.5 | G12: =Checklist!X11 | H12: =Checklist!Y11 | I12: =Checklist!L11 | J12: =IF(H12="","",IF(Checklist!N11="","",Checklist!N11)) | K12: =Checklist!Z11
F13: 1.6 | G13: =Checklist!X12 | H13: =Checklist!Y12 | I13: =Checklist!L12 | J13: =IF(H13="","",IF(Checklist!N12="","",Checklist!N12)) | K13: =Checklist!Z12 | AA13: 3 | AB13: =IF(SUM(G12:G14)=0,"",SUM(G12:G14)/($C12-(COUNTIF(G12:G14,"n/a"))))
A14: 2 | B14: Continuous Improvement | C14: 4 | D14: 1 | F14: 2.1 | G14: =Checklist!X13 | H14: =Checklist!Y13 | I14: =Checklist!L13 | J14: =IF(H14="","",IF(Checklist!N13="","",Checklist!N13)) | K14: =Checklist!Z13 | L14: =IF(SUM(G14:G17)=0,"0",SUM(G14:G17)/($C14-(COUNTIF(G14:G17,"n/a")))) -> 0 | M14: =IF(SUM(H14:H17)=0,"0",SUM(H14:H17)/($C14-(COUNTIF(H14:H17,"n/a")))) -> 0 | N14: =IF(SUM(K14:K17)=0,"0",SUM(K14:K17)/($C14-(COUNTIF(K14:K17,"n/a")))) -> 0 | AA14: 4 | AB14: =IF(SUM(G8:G11)=0,"",SUM(G8:G11)/($C8-(COUNTIF(G8:G11,"n/a"))))
F15: 2.2 | G15: =Checklist!X14 | H15: =Checklist!Y14 | I15: =Checklist!L14 | J15: =IF(H15="","",IF(Checklist!N14="","",Checklist!N14)) | K15: =Checklist!Z14 | AA15: 5 | AB15: =IF(SUM(G33:G37)=0,"",SUM(G33:G37)/($C8-(COUNTIF(G33:G37,"n/a"))))
E16: M | F16: 2.3 | G16: =Checklist!X15 | H16: =Checklist!Y15 | I16: =Checklist!L15 | J16: =IF(H16="","",IF(Checklist!N15="","",Checklist!N15)) | K16: =Checklist!Z15 | AA16: 6 | AB16: =IF(SUM(G41:G46)=0,"",SUM(G41:G46)/($C41-(COUNTIF(G41:G46,"n/a"))))
F17: 2.4 | G17: =Checklist!X16 | H17: =Checklist!Y16 | I17: =Checklist!L16 | J17: =IF(H17="","",IF(Checklist!N16="","",Checklist!N16)) | K17: =Checklist!Z16 | AA17: 15 | AB17: =IF(SUM(G74:G88)=0,"",SUM(G74:G88)/($C74-(COUNTIF(G74:G88,"n/a"))))
A18: 3 | B18: Competence Development | C18: 3 | D18: 1 | E18: M | F18: 3.1 | G18: =Checklist!X17 | H18: =Checklist!Y17 | I18: =Checklist!L17 | J18: =IF(H18="","",IF(Checklist!N17="","",Checklist!N17)) | K18: =Checklist!Z17 | L18: =IF(SUM(G18:G20)=0,"0",SUM(G18:G20)/($C18-(COUNTIF(G18:G20,"n/a")))) -> 0 | M18: =IF(SUM(H18:H20)=0,"0",SUM(H18:H20)/($C18-(COUNTIF(H18:H20,"n/a")))) -> 0 | N18: =IF(SUM(K18:K20)=0,"0",SUM(K18:K20)/($C18-(COUNTIF(K18:K20,"n/a")))) -> 0 | AB18: '=IF(COUNTA($G6,$H6)>0,"n/a",IF(I6="","",I6))
F19: 3.2 | G19: =Checklist!X18 | H19: =Checklist!Y18 | I19: =Checklist!L18 | J19: =IF(H19="","",IF(Checklist!N18="","",Checklist!N18)) | K19: =Checklist!Z18 | AB19: =SUM(COUNTIF(H8:H83,0),COUNTIF(H8:H83,40),COUNTIF(H8:H83,60),COUNTIF(H8:H83,70),COUNTIF(H8:H83,80),COUNTIF(H8:H83,100))
F20: 3.3 | G20: =Checklist!X19 | H20: =Checklist!Y19 | I20: =Checklist!L19 | J20: =IF(H20="","",IF(Checklist!N19="","",Checklist!N19)) | K20: =Checklist!Z19 | AB20: '=IF(K87="",IF(H87<>"",IF(H87>=0.7,"Acceptable",IF('Std Checklist'!CA117=0,"Action Required","Not Acceptable")),""),IF(C114="Approved", "Acceptable","Not Acceptable"))
A21: 4 | B21: Design and development of products and services | C21: 7 | D21: 3 | F21: 4.1 | G21: =Checklist!X20 | H21: =Checklist!Y20 | I21: =Checklist!L20 | J21: =IF(H21="","",IF(Checklist!N20="","",Checklist!N20)) | K21: =Checklist!Z20 | L21: =IF(SUM(G21:G27)=0,"0",SUM(G21:G27)/($C21-(COUNTIF(G21:G27,"n/a")))) -> 0 | M21: =IF(SUM(H21:H27)=0,"0",SUM(H21:H27)/($C21-(COUNTIF(H21:H27,"n/a")))) -> 0 | N21: =IF(SUM(K21:K27)=0,"0",SUM(K21:K27)/($C21-(COUNTIF(K21:K27,"n/a")))) -> 0
F22: 4.2 | G22: =Checklist!X21 | H22: =Checklist!Y21 | I22: =Checklist!L21 | J22: =IF(H22="","",IF(Checklist!N21="","",Checklist!N21)) | K22: =Checklist!Z21 | AA22: M | AB22: 1.1 | AC22: =H8
F23: 4.3 | G23: =Checklist!X22 | H23: =Checklist!Y22 | I23: =Checklist!L22 | J23: =IF(H23="","",IF(Checklist!N22="","",Checklist!N22)) | K23: =Checklist!Z22 | AA23: M | AB23: 1.2 | AC23: =H9
F24: 4.4 | G24: =Checklist!X23 | H24: =Checklist!Y23 | I24: =Checklist!L23 | J24: =IF(H24="","",IF(Checklist!N23="","",Checklist!N23)) | K24: =Checklist!Z23 | AA24: M | AB24: 1.5 | AC24: =H12
E25: M | F25: 4.5 | G25: =Checklist!X24 | H25: =Checklist!Y24 | I25: =Checklist!L24 | J25: =IF(H25="","",IF(Checklist!N24="","",Checklist!N24)) | K25: =Checklist!Z24 | AA25: M | AB25: 2.3 | AC25: =H16
E26: M | F26: 4.6 | G26: =Checklist!X25 | H26: =Checklist!Y25 | I26: =Checklist!L25 | J26: =IF(H26="","",IF(Checklist!N25="","",Checklist!N25)) | K26: =Checklist!Z25 | AA26: M | AB26: 3.1 | AC26: =H18
E27: M | F27: 4.7 | G27: =Checklist!X26 | H27: =Checklist!Y26 | I27: =Checklist!L26 | J27: =IF(H27="","",IF(Checklist!N26="","",Checklist!N26)) | K27: =Checklist!Z26 | AA27: M | AB27: 4.5 | AC27: =H25
A28: 5 | B28: Quality Planning | C28: 3 | D28: 0 | F28: 5.1 | G28: =Checklist!X27 | H28: =Checklist!Y27 | I28: =Checklist!L27 | J28: =IF(H28="","",IF(Checklist!N27="","",Checklist!N27)) | K28: =Checklist!Z27 | L28: =IF(SUM(G28:G30)=0,"0",SUM(G28:G30)/($C28-(COUNTIF(G28:G30,"n/a")))) -> 0 | M28: =IF(SUM(H28:H30)=0,"0",SUM(H28:H30)/($C28-(COUNTIF(H28:H30,"n/a")))) -> 0 | N28: =IF(SUM(K28:K30)=0,"0",SUM(K28:K30)/($C28-(COUNTIF(K28:K30,"n/a")))) -> 0 | AA28: M | AB28: 4.6 | AC28: =H26
F29: 5.2 | G29: =Checklist!X28 | H29: =Checklist!Y28 | I29: =Checklist!L28 | J29: =IF(H29="","",IF(Checklist!N28="","",Checklist!N28)) | K29: =Checklist!Z28 | AA29: M | AB29: 4.7 | AC29: =H27
F30: 5.3 | G30: =Checklist!X29 | H30: =Checklist!Y29 | I30: =Checklist!L29 | J30: =IF(H30="","",IF(Checklist!N29="","",Checklist!N29)) | K30: =Checklist!Z29 | AA30: M | AB30: 6.2 | AC30: =H32
A31: 6 | B31: Procurement | C31: 5 | D31: 3 | F31: 6.1 | G31: =Checklist!X30 | H31: =Checklist!Y30 | I31: =Checklist!L30 | J31: =IF(H31="","",IF(Checklist!N30="","",Checklist!N30)) | K31: =Checklist!Z30 | L31: =IF(SUM(G31:G35)=0,"0",SUM(G31:G35)/($C31-(COUNTIF(G31:G35,"n/a")))) -> 0 | M31: =IF(SUM(H31:H35)=0,"0",SUM(H31:H35)/($C31-(COUNTIF(H31:H35,"n/a")))) -> 0 | N31: =IF(SUM(K31:K35)=0,"0",SUM(K31:K35)/($C31-(COUNTIF(K31:K35,"n/a")))) -> 0 | AA31: M | AB31: 6.3 | AC31: =H33
E32: M | F32: 6.2 | G32: =Checklist!X31 | H32: =Checklist!Y31 | I32: =Checklist!L31 | J32: =IF(H32="","",IF(Checklist!N31="","",Checklist!N31)) | K32: =Checklist!Z31 | AA32: M | AB32: 6.4 | AC32: =H34
E33: M | F33: 6.3 | G33: =Checklist!X32 | H33: =Checklist!Y32 | I33: =Checklist!L32 | J33: =IF(H33="","",IF(Checklist!N32="","",Checklist!N32)) | K33: =Checklist!Z32 | AA33: M | AB33: 7.1 | AC33: =H36
E34: M | F34: 6.4 | G34: =Checklist!X33 | H34: =Checklist!Y33 | I34: =Checklist!L33 | J34: =IF(H34="","",IF(Checklist!N33="","",Checklist!N33)) | K34: =Checklist!Z33 | AA34: M | AB34: 7.2 | AC34: =H37
F35: 6.5 | G35: =Checklist!X34 | H35: =Checklist!Y34 | I35: =Checklist!L34 | J35: =IF(H35="","",IF(Checklist!N34="","",Checklist!N34)) | K35: =Checklist!Z34 | AA35: M | AB35: 7.3 | AC35: =H38
A36: 7 | B36: Incoming Material | C36: 3 | D36: 3 | E36: M | F36: 7.1 | G36: =Checklist!X35 | H36: =Checklist!Y35 | I36: =Checklist!L35 | J36: =IF(H36="","",IF(Checklist!N35="","",Checklist!N35)) | K36: =Checklist!Z35 | L36: =IF(SUM(G36:G38)=0,"0",SUM(G36:G38)/($C36-(COUNTIF(G36:G38,"n/a")))) -> 0 | M36: =IF(SUM(H36:H38)=0,"0",SUM(H36:H38)/($C36-(COUNTIF(H36:H38,"n/a")))) -> 0 | N36: =IF(SUM(K36:K38)=0,"0",SUM(K36:K38)/($C36-(COUNTIF(K36:K38,"n/a")))) -> 0 | AA36: M | AB36: 8.2 | AC36: =H40
E37: M | F37: 7.2 | G37: =Checklist!X36 | H37: =Checklist!Y36 | I37: =Checklist!L36 | J37: =IF(H37="","",IF(Checklist!N36="","",Checklist!N36)) | K37: =Checklist!Z36 | AA37: M | AB37: 8.4 | AC37: =H42
E38: M | F38: 7.3 | G38: =Checklist!X37 | H38: =Checklist!Y37 | I38: =Checklist!L37 | J38: =IF(H38="","",IF(Checklist!N37="","",Checklist!N37)) | K38: =Checklist!Z37 | AA38: M | AB38: 8.5 | AC38: =H43
A39: 8 | B39: Manufacturing Quality | C39: 9 | D39: 3 | F39: 8.1 | G39: =Checklist!X38 | H39: =Checklist!Y38 | I39: =Checklist!L38 | J39: =IF(H39="","",IF(Checklist!N38="","",Checklist!N38)) | K39: =Checklist!Z38 | L39: =IF(SUM(G39:G47)=0,"0",SUM(G39:G47)/($C39-(COUNTIF(G39:G47,"n/a")))) -> 0 | M39: =IF(SUM(H39:H47)=0,"0",SUM(H39:H47)/($C39-(COUNTIF(H39:H47,"n/a")))) -> 0 | N39: =+IF(SUM(K39:K47)=0,"0",SUM(K39:K47)/($C39-(COUNTIF(K39:K47,"n/a")))) -> 0 | AA39: M | AB39: 9.1 | AC39: =H48
E40: M | F40: 8.2 | G40: =Checklist!X39 | H40: =Checklist!Y39 | I40: =Checklist!L39 | J40: =IF(H40="","",IF(Checklist!N39="","",Checklist!N39)) | K40: =Checklist!Z39 | AA40: M | AB40: 9.4 | AC40: =H51
F41: 8.3 | G41: =Checklist!X40 | H41: =Checklist!Y40 | I41: =Checklist!L40 | J41: =IF(H41="","",IF(Checklist!N40="","",Checklist!N40)) | K41: =Checklist!Z40 | AA41: M | AB41: 10.2 | AC41: =H53
E42: M | F42: 8.4 | G42: =Checklist!X41 | H42: =Checklist!Y41 | I42: =Checklist!L41 | J42: =IF(H42="","",IF(Checklist!N41="","",Checklist!N41)) | K42: =Checklist!Z41 | AA42: M | AB42: 11.3 | AC42: =H58
E43: M | F43: 8.5 | G43: =Checklist!X42 | H43: =Checklist!Y42 | I43: =Checklist!L42 | J43: =IF(H43="","",IF(Checklist!N42="","",Checklist!N42)) | K43: =Checklist!Z42 | AA43: M | AB43: 12.3 | AC43: =H61
F44: 8.6 | G44: =Checklist!X43 | H44: =Checklist!Y43 | I44: =Checklist!L43 | J44: =IF(H44="","",IF(Checklist!N43="","",Checklist!N43)) | K44: =Checklist!Z43 | AA44: M | AB44: 12.5 | AC44: =H63
F45: 8.7 | G45: =Checklist!X44 | H45: =Checklist!Y44 | I45: =Checklist!L44 | J45: =IF(H45="","",IF(Checklist!N44="","",Checklist!N44)) | K45: =Checklist!Z44
F46: 8.8 | G46: =Checklist!X45 | H46: =Checklist!Y45 | I46: =Checklist!L45 | J46: =IF(H46="","",IF(Checklist!N45="","",Checklist!N45)) | K46: =Checklist!Z45
F47: 8.9 | G47: =Checklist!X46 | H47: =Checklist!Y46 | I47: =Checklist!L46 | J47: =IF(H47="","",IF(Checklist!N46="","",Checklist!N46)) | K47: =Checklist!Z46
A48: 9 | B48: Nonconformity Control | C48: 4 | D48: 2 | E48: M | F48: 9.1 | G48: =Checklist!X47 | H48: =Checklist!Y47 | I48: =Checklist!L47 | J48: =IF(H48="","",IF(Checklist!N47="","",Checklist!N47)) | K48: =Checklist!Z47 | L48: =IF(SUM(G48:G51)=0,"0",SUM(G48:G51)/($C48-(COUNTIF(G48:G51,"n/a")))) -> 0 | M48: =IF(SUM(H48:H51)=0,"0",SUM(H48:H51)/($C48-(COUNTIF(H48:H51,"n/a")))) -> 0 | N48: =IF(SUM(K48:K51)=0,"0",SUM(K48:K51)/($C48-(COUNTIF(K48:K51,"n/a")))) -> 0 | AA48: Audit Team Recommendation Choices
F49: 9.2 | G49: =Checklist!X48 | H49: =Checklist!Y48 | I49: =Checklist!L48 | J49: =IF(H49="","",IF(Checklist!N48="","",Checklist!N48)) | K49: =Checklist!Z48 | AA49: Passed
F50: 9.3 | G50: =Checklist!X49 | H50: =Checklist!Y49 | I50: =Checklist!L49 | J50: =IF(H50="","",IF(Checklist!N49="","",Checklist!N49)) | K50: =Checklist!Z49 | AA50: Conditional Approval
E51: M | F51: 9.4 | G51: =Checklist!X50 | H51: =Checklist!Y50 | I51: =Checklist!L50 | J51: =IF(H51="","",IF(Checklist!N50="","",Checklist!N50)) | K51: =Checklist!Z50 | AA51: Rejected
A52: 10 | B52: Measurement Equipment | C52: 4 | D52: 1 | F52: 10.1 | G52: =Checklist!X51 | H52: =Checklist!Y51 | I52: =Checklist!L51 | J52: =IF(H52="","",IF(Checklist!N51="","",Checklist!N51)) | K52: =Checklist!Z51 | L52: =IF(SUM(G52:G55)=0,"0",SUM(G52:G55)/($C52-(COUNTIF(G52:G55,"n/a")))) -> 0 | M52: =IF(SUM(H52:H55)=0,"0",SUM(H52:H55)/($C52-(COUNTIF(H52:H55,"n/a")))) -> 0 | N52: =IF(SUM(K52:K55)=0,"0",SUM(K52:K55)/($C52-(COUNTIF(K52:K55,"n/a")))) -> 0
E53: M | F53: 10.2 | G53: =Checklist!X52 | H53: =Checklist!Y52 | I53: =Checklist!L52 | J53: =IF(H53="","",IF(Checklist!N52="","",Checklist!N52)) | K53: =Checklist!Z52 | AA53: Final Disposition Choices
F54: 10.3 | G54: =Checklist!X53 | H54: =Checklist!Y53 | I54: =Checklist!L53 | J54: =IF(H54="","",IF(Checklist!N53="","",Checklist!N53)) | K54: =Checklist!Z53
F55: 10.4 | G55: =Checklist!X54 | H55: =Checklist!Y54 | I55: =Checklist!L54 | J55: =IF(H55="","",IF(Checklist!N54="","",Checklist!N54)) | K55: =Checklist!Z54 | AA55: Passed
A56: 11 | B56: Preventive Maintenance | C56: 3 | D56: 1 | F56: 11.1 | G56: =Checklist!X55 | H56: =Checklist!Y55 | I56: =Checklist!L55 | J56: =IF(H56="","",IF(Checklist!N55="","",Checklist!N55)) | K56: =Checklist!Z55 | L56: =IF(SUM(G56:G58)=0,"0",SUM(G56:G58)/($C56-(COUNTIF(G56:G58,"n/a")))) -> 0 | M56: =IF(SUM(H56:H58)=0,"0",SUM(H56:H58)/($C56-(COUNTIF(H56:H58,"n/a")))) -> 0 | N56: =IF(SUM(K56:K58)=0,"0",SUM(K56:K58)/($C56-(COUNTIF(K56:K58,"n/a")))) -> 0 | AA56: Conditional Approval
F57: 11.2 | G57: =Checklist!X56 | H57: =Checklist!Y56 | I57: =Checklist!L56 | J57: =IF(H57="","",IF(Checklist!N56="","",Checklist!N56)) | K57: =Checklist!Z56 | AA57: Rejected
E58: M | F58: 11.3 | G58: =Checklist!X57 | H58: =Checklist!Y57 | I58: =Checklist!L57 | J58: =IF(H58="","",IF(Checklist!N57="","",Checklist!N57)) | K58: =Checklist!Z57
A59: 12 | B59: Storage & Packaging | C59: 5 | D59: 2 | F59: 12.1 | G59: =Checklist!X58 | H59: =Checklist!Y58 | I59: =Checklist!L58 | J59: =IF(H59="","",IF(Checklist!N58="","",Checklist!N58)) | K59: =Checklist!Z58 | L59: =IF(SUM(G59:G63)=0,"0",SUM(G59:G63)/($C59-(COUNTIF(G59:G63,"n/a")))) -> 0 | M59: =IF(SUM(H59:H63)=0,"0",SUM(H59:H63)/($C59-(COUNTIF(H59:H63,"n/a")))) -> 0 | N59: =IF(SUM(K59:K63)=0,"0",SUM(K59:K63)/($C59-(COUNTIF(K59:K63,"n/a")))) -> 0 | AA59: Guidelines for Assigning Audit Team Recommendation & Final Disposition
F60: 12.2 | G60: =Checklist!X59 | H60: =Checklist!Y59 | I60: =Checklist!L59 | J60: =IF(H60="","",IF(Checklist!N59="","",Checklist!N59)) | K60: =Checklist!Z59 | AA60: The Audit Team Recommendation (ATR) and Final Disposition (FD) are automatically assigned using the four guidelines below.
E61: M | F61: 12.3 | G61: =Checklist!X60 | H61: =Checklist!Y60 | I61: =Checklist!L60 | J61: =IF(H61="","",IF(Checklist!N60="","",Checklist!N60)) | K61: =Checklist!Z60 | AA61: In all cases, it is very important that Corrective Actions are verified to ensure the supplier has met the Requirement and the effected scores can be adjusted to 70% or above prior to production/shipping of Vertiv part numbers. The Corrective Action follow-up is typically the responsibility of the Division that will be using the parts/materials.
F62: 12.4 | G62: =Checklist!X61 | H62: =Checklist!Y61 | I62: =Checklist!L61 | J62: =IF(H62="","",IF(Checklist!N61="","",Checklist!N61)) | K62: =Checklist!Z61 | AA62: If Total Mandatory Requirements Score AND On-Site Overall Score = 70 or Greater then Audit Team Recommendation will be "Acceptable" and Final Disposition will be "Approved"
E63: M | F63: 12.5 | G63: =Checklist!X62 | H63: =Checklist!Y62 | I63: =Checklist!L62 | J63: =IF(H63="","",IF(Checklist!N62="","",Checklist!N62)) | K63: =Checklist!Z62
A64: 13 | B64: Environmental | C64: 4 | D64: 0 | F64: 13.1 | G64: =Checklist!X63 | H64: =Checklist!Y63 | I64: =Checklist!L63 | J64: =IF(H64="","",IF(Checklist!N63="","",Checklist!N63)) | K64: =Checklist!Z63 | L64: =IF(SUM(G64:G67)=0,"0",SUM(G64:G67)/($C64-(COUNTIF(G64:G67,"n/a")))) -> 0 | M64: =IF(SUM(H64:H67)=0,"0",SUM(H64:H67)/($C64-(COUNTIF(H64:H67,"n/a")))) -> 0 | N64: =IF(SUM(K64:K67)=0,"0",SUM(K64:K67)/($C64-(COUNTIF(K64:K67,"n/a")))) -> 0 | AA64: If Total Mandatory Requirements Score OR On-Site Overall Score = 69 or Less and supplier has no corrective actions assigned then Audit Team Recommendation will be "Not Acceptable" and Final Disposition will be "Not Approved-Division will not buy from supplier"
F65: 13.2 | G65: =Checklist!X64 | H65: =Checklist!Y64 | I65: =Checklist!L64 | J65: =IF(H65="","",IF(Checklist!N64="","",Checklist!N64)) | K65: =Checklist!Z64 | AA65: If After CAPA Verif. SCORE = 69 or Less then Final Disposition will be "Not Approved-Division will not buy from supplier"
F66: 13.3 | G66: =Checklist!X65 | H66: =Checklist!Y65 | I66: =Checklist!L65 | J66: =IF(H66="","",IF(Checklist!N65="","",Checklist!N65)) | K66: =Checklist!Z65 | AA66: If After CAPA Verif. SCORE = 70 or Greater then Final Disposition will be "Approved"
F67: 13.4 | G67: =Checklist!X66 | H67: =Checklist!Y66 | I67: =Checklist!L66 | J67: =IF(H67="","",IF(Checklist!N66="","",Checklist!N66)) | K67: =Checklist!Z66 | AA67: Removed: If Total Mandatory Requirements Score OR On-Site Overall Score = 69 or Less and supplier has no corrective actions assigned then Audit Team Recommendation will be "Not Acceptable" and Final Disposition will be "Not Approved-Division will not buy from supplier"
A68: 14 | B68: Occupational Health & Safety | C68: 3 | D68: 0 | F68: 14.1 | G68: =Checklist!X67 | H68: =Checklist!Y67 | I68: =Checklist!L67 | J68: =IF(H68="","",IF(Checklist!N67="","",Checklist!N67)) | K68: =Checklist!Z67 | L68: =IF(SUM(G68:G70)=0,"0",SUM(G68:G70)/($C68-(COUNTIF(G68:G70,"n/a")))) -> 0 | M68: =IF(SUM(H68:H70)=0,"0",SUM(H68:H70)/($C68-(COUNTIF(H68:H70,"n/a")))) -> 0 | N68: =IF(SUM(K68:K70)=0,"0",SUM(K68:K70)/($C68-(COUNTIF(K68:K70,"n/a")))) -> 0
F69: 14.2 | G69: =Checklist!X68 | H69: =Checklist!Y68 | I69: =Checklist!L68 | J69: =IF(H69="","",IF(Checklist!N68="","",Checklist!N68)) | K69: =Checklist!Z68
F70: 14.3 | G70: =Checklist!X69 | H70: =Checklist!Y69 | I70: =Checklist!L69 | J70: =IF(H70="","",IF(Checklist!N69="","",Checklist!N69)) | K70: =Checklist!Z69
A71: 15 | B71: Corporate Compliance (ROHS) | C71: 5 | D71: 0 | F71: 15.1 | G71: =Checklist!X70 | H71: =Checklist!Y70 | I71: =Checklist!L70 | J71: =IF(H71="","",IF(Checklist!N70="","",Checklist!N70)) | K71: =Checklist!Z70 | L71: =IF(SUM(G71:G75)=0,"0",SUM(G71:G75)/($C71-(COUNTIF(G71:G75,"n/a")))) -> 0 | M71: =IF(SUM(H71:H75)=0,"0",SUM(H71:H75)/($C71-(COUNTIF(H71:H75,"n/a")))) -> 0 | N71: =IF(SUM(K71:K75)=0,"0",SUM(K71:K75)/($C71-(COUNTIF(K71:K75,"n/a")))) -> 0
F72: 15.2 | G72: =Checklist!X71 | H72: =Checklist!Y71 | I72: =Checklist!L71 | J72: =IF(H72="","",IF(Checklist!N71="","",Checklist!N71)) | K72: =Checklist!Z71
F73: 15.3 | G73: =Checklist!X72 | H73: =Checklist!Y72 | I73: =Checklist!L72 | J73: =IF(H73="","",IF(Checklist!N72="","",Checklist!N72)) | K73: =Checklist!Z72
F74: 15.4 | G74: =Checklist!X73 | H74: =Checklist!Y73 | I74: =Checklist!L73 | J74: =IF(H74="","",IF(Checklist!N73="","",Checklist!N73)) | K74: =Checklist!Z73
F75: 15.5 | G75: =Checklist!X74 | H75: =Checklist!Y74 | I75: =Checklist!L74 | J75: =IF(H75="","",IF(Checklist!N74="","",Checklist!N74)) | K75: =Checklist!Z74
A76: 16 | B76: Corporate Compliance (REACH) | C76: 5 | D76: 0 | F76: 16.1 | G76: =Checklist!X75 | H76: =Checklist!Y75 | I76: =Checklist!L75 | J76: =IF(H76="","",IF(Checklist!N75="","",Checklist!N75)) | K76: =Checklist!Z75 | L76: =IF(SUM(G76:G80)=0,"0",SUM(G76:G80)/($C76-(COUNTIF(G76:G80,"n/a")))) -> 0 | M76: =IF(SUM(H76:H80)=0,"0",SUM(H76:H80)/($C76-(COUNTIF(H76:H80,"n/a")))) -> 0 | N76: =IF(SUM(K76:K80)=0,"0",SUM(K76:K80)/($C76-(COUNTIF(K76:K80,"n/a")))) -> 0
F77: 16.2 | G77: =Checklist!X76 | H77: =Checklist!Y76 | I77: =Checklist!L76 | J77: =IF(H77="","",IF(Checklist!N76="","",Checklist!N76)) | K77: =Checklist!Z76
F78: 16.3 | G78: =Checklist!X77 | H78: =Checklist!Y77 | I78: =Checklist!L77 | J78: =IF(H78="","",IF(Checklist!N77="","",Checklist!N77)) | K78: =Checklist!Z77
F79: 16.4 | G79: =Checklist!X78 | H79: =Checklist!Y78 | I79: =Checklist!L78 | J79: =IF(H79="","",IF(Checklist!N78="","",Checklist!N78)) | K79: =Checklist!Z78
F80: 16.5 | G80: =Checklist!X79 | H80: =Checklist!Y79 | I80: =Checklist!L79 | J80: =IF(H80="","",IF(Checklist!N79="","",Checklist!N79)) | K80: =Checklist!Z79
A81: 17 | B81: Corporate Compliance (Conflict Minerals) | C81: 3 | D81: 0 | F81: 17.1 | G81: =Checklist!X80 | H81: =Checklist!Y80 | I81: =Checklist!L80 | J81: =IF(H81="","",IF(Checklist!N80="","",Checklist!N80)) | K81: =Checklist!Z80 | L81: =IF(SUM(G81:G83)=0,"0",SUM(G81:G83)/($C81-(COUNTIF(G81:G83,"n/a")))) -> 0 | M81: =IF(SUM(H81:H83)=0,"0",SUM(H81:H83)/($C81-(COUNTIF(H81:H83,"n/a")))) -> 0 | N81: =IF(SUM(K81:K83)=0,"0",SUM(K81:K83)/($C81-(COUNTIF(K81:K83,"n/a")))) -> 0
F82: 17.2 | G82: =Checklist!X81 | H82: =Checklist!Y81 | I82: =Checklist!L81 | J82: =IF(H82="","",IF(Checklist!N81="","",Checklist!N81)) | K82: =Checklist!Z81
F83: 17.3 | G83: =Checklist!X82 | H83: =Checklist!Y82 | I83: =Checklist!L82 | J83: =IF(H83="","",IF(Checklist!N82="","",Checklist!N82)) | K83: =Checklist!Z82
A84: 18 | B84: Corporate Compliance (Code of Conduct) | C84: 4 | D84: 0 | F84: 18.1 | G84: =Checklist!X83 | H84: =Checklist!Y83 | I84: =Checklist!L83 | J84: =IF(H84="","",IF(Checklist!N83="","",Checklist!N83)) | K84: =Checklist!Z83 | L84: =IF(SUM(G84:G87)=0,"0",SUM(G84:G87)/($C84-(COUNTIF(G84:G87,"n/a")))) -> 0 | M84: =IF(SUM(H84:H87)=0,"0",SUM(H84:H87)/($C84-(COUNTIF(H84:H87,"n/a")))) -> 0 | N84: =IF(SUM(K84:K87)=0,"0",SUM(K84:K87)/($C84-(COUNTIF(K84:K87,"n/a")))) -> 0
F85: 18.2 | G85: =Checklist!X84 | H85: =Checklist!Y84 | I85: =Checklist!L84 | J85: =IF(H85="","",IF(Checklist!N84="","",Checklist!N84)) | K85: =Checklist!Z84
F86: 18.3 | G86: =Checklist!X85 | H86: =Checklist!Y85 | I86: =Checklist!L85 | J86: =IF(H86="","",IF(Checklist!N85="","",Checklist!N85)) | K86: =Checklist!Z85
F87: 18.4 | G87: =Checklist!X86 | H87: =Checklist!Y86 | I87: =Checklist!L86 | J87: =IF(H87="","",IF(Checklist!N86="","",Checklist!N86)) | K87: =Checklist!Z86
A88: No. Possible | C88: =SUM(C8:C87) -> 80 | D88: =SUM(D8:D87) -> 23 | G88: =SUM(G8,G9,G12,G16,G25,G18,G26,G27,G32,G33,G34,G36,G37,G42,G38,G40,G43,G48,G51,G53,G58,G61,G63)/$D$88/100 -> 0 | H88: =SUM(H8,H9,H12,H16,H25,H18,H26,H27,H32,H33,H34,H36,H37,H42,H38,H40,H43,H48,H51,H53,H58,H61,H63)/$D$88/100 -> 0 | I88: {=SUM(IF($E$8:$E$87="M",1,0)*IF($I$8:$I$87="Y",1,0))} -> 0 | J88: {=SUM(IF($E$8:$E$87="M",1,0)*IF($J$8:$J$87="Open",1,0))} -> 0 | K88: =SUM(K8,K9,K12,K16,K25,K18,K26,K27,K32,K33,K34,K36,K37,K42,K38,K40,K43,K48,K51,K53,K58,K61,K63)/$D$88/100 -> 0 | L88: MANDATORY ONLY
A89: No. of Requirements Audited: | C89: =C88-COUNTIF(H8:H87,"n/a")-COUNTIF(H8:H87,"") -> 0 | D89: =D88-COUNTIF(AC22:AC44,"")-COUNTIF(AC22:AC44,"n/a") -> 0 | G89: =Checklist!H91 -> 0 | H89: =Checklist!I91 -> 0 | I89: =COUNTIF(I8:I87,"Y") -> 0 | J89: =COUNTIF(J8:J87,"Open") -> 0 | K89: =Checklist!J91 -> 0 | L89: Final Checklist Score | AA89: =(Checklist!I89+'Technical Assessment - Generic'!H17)/(Checklist!H90+'Technical Assessment - Generic'!H18) -> 0
A90: *Link to "Technical assessment - Generic" Tab | H90: ='Technical Assessment - Generic'!H19 -> 0 | I90: ='Technical Assessment - Generic'!K21 -> 0 | J90: ='Technical Assessment - Generic'!M21 -> 0 | K90: ='Technical Assessment - Generic'!I19 -> 0 | L90: Additional Requirement | AA90: =(Checklist!J89+'Technical Assessment - Generic'!I17)/(Checklist!J90+'Technical Assessment - Generic'!I18) -> 0
A91: Remark: in case there are additional requirements, add to "Technical asseseement-Generic" Tab. | H91: =IF(H90=0,H89,AA89) -> 0 | I91: =I89+I90 -> 0 | J91: =J89+J90 -> 0 | K91: =IF(K90=0,K89,AA90) -> 0 | L91: OVERALL | M91: Weighted ave. scores (Req's & Add. Req's)_Row 89 & 90 | AA91: L131 was =IF(H126="","",IF(H118>=0.7,IF(H126>=0.7,"Acceptable","Action Required"),"Action Required"))
A93: AUDIT TEAM Conclusion
H94: On-Site Audit SCORE | I94: CA Req'd? (Y) | J94: CA Status (Open) | K94: After CA Verif. SCORE | L94: CONCLUSIONS
A95: SCORING SUMMARY | C95: Mandatory Requirements Only | J95: =COUNTIFS(E8:E87,"M",J8:J87,"Open") -> 0 | K95: =K88 -> 0 | L95: =IF(J95=0,"Passed",IF(K95>=0.7,"Passed","Action Required")) -> Passed
C96: On-Site Overall Score | H96: =H91 -> 0 | L96: =IF(H96=0,"",IF(J91=0,"",IF(H96>=0.7,"Passed","Action Required")))
C97: CA's Assigned at On-Site Audit | I97: =I91 -> 0 | L97: =IF(H91=0,"",IF(J91=0,"",IF(I97>=1,"Action Required","Passed")))
C98: CA's Open After Verification Audit | J98: =J91 -> 0 | L98: =IF(H91=0,"",IF(J98>=1,"Action Required","Passed"))
C99: After CA Verified Score | K99: =K91 -> 0 | L99: =IF(K99=0,"",IF(K99>=0.7,"Passed","Action Required"))
A101: AUDIT TEAM CONCLUSION | C101: Mandatory Req'mnts Score | E101: =H88 -> 0 | G101: On-Site Audit Score | I101: =H91 -> 0 | J101: VSAC Result | L101: =IF(AND(E101>=70%,I101>=70%),"Passed",IF(AND(E101>=60%,I101>=60%),"Conditional Approved",IF(OR(E101<60%,I101<60%),"Rejected",""))) -> Rejected
A102: Instructions: Complete 'On-Site Audit' scores & provide details of any Requirements scoring less than 70 on the Checklist & the Added Requirements tab (if applicable). Allow time for the supplier to take corrective active & provide objective evidence. Review the supplier's actions & update the 'After CA Verification' scores appropriately. Enter any "specific conditions" in the Comments box(es), dates & other information as necessary.
...

Sheet Technical Assessment - Generic
D1: Supplier to complete light-green cells | E1: Vertiv to complete light-yellow cells | H1: =COUNTIF(H7:H13,100) -> 0 | I1: =COUNTIF(I7:I13,100) -> 0 | J1: =IF(SUM($H$1:$I$1)>=2,"Refer to VSAC Auditor Scoring Guide when using score of '100'.","") | N1: VSAC-Report-Template-2021 V1c | S1: Correct Row Order | W1: Hide >> | AA1: Supplier Self-Audit | AH1: Status | AI1: << Hide
W2: Hide >> | AA2: On-Site Audit | AB2: 0 | AC2: 40 | AD2: 60 | AE2: 70 | AF2: 80 | AG2: 100 | AH2: Open | AI2: << Hide
D3: Technical Assessment | E3: =IF('Supplier Profile & Audit Plan'!$A$6="","",'Supplier Profile & Audit Plan'!$A$6) -> Savannah Tank & Equipment Corp. | F3: Not Applicable | G3: Not Verified | H3: On-Site Audit SCORE | I3: After CA Verif. SCORE | J3: AUDIT FINDINGS & OBSERVATIONS | K3: Supplier CA Req'd? (Y / N) | L3: Completion Date (mm/dd/yyyy) | M3: CA Status | N3: ROOT CAUSE & Scope of Problem Including Other Areas | O3: REMEDIAL ACTION Immediate Actions Taken to Address Issue / Finding | P3: CORRECTIVE ACTION Taken to Address Root Cause & Prevent Recurrence | Q3: PREVENTIVE ACTION Actions Taken to Prevent Similar Issues in Other Areas | R3: CONTROLS Deployed to Monitor CA/PA Effectiveness | W3: Hide >> | X3: On-Site Score (w/o n/a's) | Y3: After Verif .Score (w/o n/a's) | AA3: Adjusted | AB3: 0 | AC3: 40 | AD3: 60 | AE3: 70 | AF3: 80 | AG3: 100 | AH3: Closed | AI3: << Hide
D4: =IF('Supplier Profile & Audit Plan'!$A$47>0,'Supplier Profile & Audit Plan'!$A$47,'Supplier Profile & Audit Plan'!$A$46) -> TBD | E4: =IF('Supplier Profile & Audit Plan'!$A$49="","",'Supplier Profile & Audit Plan'!$A$49) -> Sheet Metal & Enclosure | W4: Hide >> | AH4: <blank> | AI4: << Hide
D5: General Requirements | E5: Specific Requirements for Product Type | W5: Hide >> | AI5: << Hide
D6: Go to: Findings | E6: Go to: Corrective Actions | J6: Go to: Scoring Guidelines | N6: Go to: Corrective Action Instructions | W6: Hide >> | AI6: << Hide
A7: Bottom | B7: 1.0 PRODUCT / PROCESS KNOWLEDGE | C7: 1.1 | D7: Product Knowledge Supplier has adequate experience in design / development and manufacture of similar products | K7: =IF(H7="","",IF(F7<>"","",IF(H7>=70,"N","Y"))) | M7: =IF(H7="","",IF(H7>=70,"",IF(SUM(IF(H7>=70,1,-1)+IF(I7>=70,1,-1))>=0,"Closed","Open"))) | S7: 1 | W7: Hide >> | X7: =IF(COUNTA($F7,$G7)>0,"n/a",IF(H7="","",H7)) | Y7: =IF(COUNTA($F7,$G7)>0,"n/a",IF(I7="","",I7)) | AI7: << Hide
A8: 1 | C8: 1.2 | D8: Process Knowledge Expert understanding of typical requirements (e.g. performance, cosmetic, functional) and how to manufacture to meet requirements; understanding of key process parameters and how they are controlled. | E8: Adequate engineering resources to design or modify Vertiv products | S8: 2 | W8: Hide >> | X8: =IF(COUNTA($F8,$G8)>0,"n/a",IF(H8="","",H8)) | Y8: =IF(COUNTA($F8,$G8)>0,"n/a",IF(I8="","",I8)) | AI8: << Hide
A9: 2 | B9: 2.0 MANUFACTURING EQUIPMENT/TOOLS | C9: 2.1 | D9: Manufacturing Equipment Supplier has appropriate machines and tooling to manufacture product Supplier has adequate capacity including: 1) Equipment and tooling; 2) Manpower; 3) Floor space; 4) Adequate time for PM or unscheduled downtime; 5) Increased demand. | K9: =IF(H9="","",IF(F9<>"","",IF(H9>=70,"N","Y"))) | M9: =IF(H9="","",IF(H9>=70,"",IF(SUM(IF(H9>=70,1,-1)+IF(I9>=70,1,-1))>=0,"Closed","Open"))) | S9: 5 | W9: Hide >> | X9: =IF(COUNTA($F9,$G9)>0,"n/a",IF(H9="","",H9)) | Y9: =IF(COUNTA($F9,$G9)>0,"n/a",IF(I9="","",I9)) | AI9: << Hide
A10: 3 | C10: 2.2 | D10: Production Environment Supplier's factory environment is appropriate for manufacture of Vertiv product within specifications | E10: Presence of a clean room ESD equipment and program Temperature and humidity control | K10: =IF(H10="","",IF(F10<>"","",IF(H10>=70,"N","Y"))) | M10: =IF(H10="","",IF(H10>=70,"",IF(SUM(IF(H10>=70,1,-1)+IF(I10>=70,1,-1))>=0,"Closed","Open"))) | S10: 6 | X10: =IF(COUNTA($F10,$G10)>0,"n/a",IF(H10="","",H10)) | Y10: =IF(COUNTA($F10,$G10)>0,"n/a",IF(I10="","",I10))
A11: 4 | C11: 2.3 | D11: Testing Equipment/Capability Supplier has fixtures, measurement and testing equipment for Vertiv products | K11: =IF(H11="","",IF(F11<>"","",IF(H11>=70,"N","Y"))) | M11: =IF(H11="","",IF(H11>=70,"",IF(SUM(IF(H11>=70,1,-1)+IF(I11>=70,1,-1))>=0,"Closed","Open"))) | S11: 7 | W11: Hide >> | X11: =IF(COUNTA($F11,$G11)>0,"n/a",IF(H11="","",H11)) | Y11: =IF(COUNTA($F11,$G11)>0,"n/a",IF(I11="","",I11)) | AI11: << Hide
A12: Bottom | B12: 3.0 ABILITY TO MEET DRAWINGS & SPECIFICATIONS | C12: 3.1 | D12: Clear understanding of VERTIV's tolerances, specifications, agency requirements, functional and testing requirements. | E12: UL, IPC | K12: =IF(H12="","",IF(F12<>"","",IF(H12>=70,"N","Y"))) | M12: =IF(H12="","",IF(H12>=70,"",IF(SUM(IF(H12>=70,1,-1)+IF(I12>=70,1,-1))>=0,"Closed","Open"))) | S12: 9 | W12: Hide >> | X12: =IF(COUNTA($F12,$G12)>0,"n/a",IF(H12="","",H12)) | Y12: =IF(COUNTA($F12,$G12)>0,"n/a",IF(I12="","",I12)) | AI12: << Hide
A13: 1 | C13: 3.2 | D13: Proven ability to meet all requirements as demonstrated via compliance to either VERTIV or equivalent requirements by prototype part submissions, current production, etc | K13: =IF(H13="","",IF(F13<>"","",IF(H13>=70,"N","Y"))) | M13: =IF(H13="","",IF(H13>=70,"",IF(SUM(IF(H13>=70,1,-1)+IF(I13>=70,1,-1))>=0,"Closed","Open"))) | S13: 10 | W13: Hide >> | X13: =IF(COUNTA($F13,$G13)>0,"n/a",IF(H13="","",H13)) | Y13: =IF(COUNTA($F13,$G13)>0,"n/a",IF(I13="","",I13)) | AI13: << Hide
A14: 2 | B14: 4.0 ADDITIONAL REQUIREMENTS | C14: 4 | D14: XXX - This row is for Vertiv SQE to write down the additional requirements if there is any. Please place "x" in "Not Applicable" Cell F14 if there is no “additional requirement”. | K14: =IF(H14="","",IF(F14<>"","",IF(H14>=70,"N","Y"))) | M14: =IF(H14="","",IF(H14>=70,"",IF(SUM(IF(H14>=70,1,-1)+IF(I14>=70,1,-1))>=0,"Closed","Open"))) | S14: 11 | X14: =IF(COUNTA($F14,$G14)>0,"n/a",IF(H14="","",H14)) | Y14: =IF(COUNTA($F14,$G14)>0,"n/a",IF(I14="","",I14))
A15: . | S15: .
D16: TOTAL SCORES FOR THIS CHECKLIST ONLY | F16: Not Applicable | G16: Not Verified | H16: On-Site Audit Std Chklst SCORE | I16: After CAPA Verif. Std Chklst SCORE | K16: On-Site Audit Findings | AJ16: Pass
D17: Sum of Scores (excluding "n/a" & "Not Verified"): | H17: =SUM($X$7:$X$14) -> 0 | I17: =SUM($Y$7:$Y$14) -> 0 | K17: Corrective Action plans will be submitted on (date): | AJ17: Fail
E18: Maximum Total Score Available: | F18: =COUNTA(F7:F14) -> 0 | G18: =COUNTA(G7:G14) -> 0 | H18: =(COUNTA($D$7:$D$14)-($F18+$G18))*100 -> 800 | I18: =(COUNTA($D$7:$D$14)-($F18+$G18))*100 -> 800 | K18: Vertiv Audit Leader (name & title):
E19: Standard Checklist Score: | H19: =(H17/H18) -> 0 | I19: =(I17/I18) -> 0 | K19: Supplier QA Representative (name & title):
D20: Date: | F20: =IF('Supplier Profile & Audit Plan'!$A$47="","",'Supplier Profile & Audit Plan'!$A$47) -> TBD | K20: CA-PA Verification & Finding Closure Date:
K21: =COUNTIF(K7:K14,"Y") -> 0 | M21: =COUNTIF(M7:M14,"Open") -> 0
G22: Summary and Conclusion:
D24: Vertiv auditor to use scoring instructions below when assigning On-Site Audit Score. | R24: Top
D25: Scoring Instructions for Vertiv On-Site Audit
D26: Based on On-Site audit evidence, select score that best describes level of compliance to the Requirement. If Requirement does not apply to product to be purchased, place "x" in the "Not Applicable" column.
D27: 0 = NO EVIDENCE PROVIDED; Corrective action required
D28: 40 = RARELY COMPLIES; Corrective action required
D29: 60 = SOME NON-COMPLIANCES; Corrective action required
D30: 70 = NO NON-COMPLIANCES; Meets Minimum Requirement / No CA required
D31: 80 = NO NON-COMPLIANCES; Exceeds Minimum Requirement / No CA required
D32: 100 = NO NON-COMPLIANCES; Excellent / Highly commendable
D33: Supplier Corrective Action plan
D34: Supplier must record their corrective and preventive actions that will address each Finding. This is typed in the columns to the right of Findings on the Standard Checklist.
D35: Supplier Corrective Action & Preventive Action (CAPA) plan must address:
D36: Root Cause of the problem; should look beyond specific incident cited in Finding
... D38: Corrective Action; actions to address root cause and prevent recurrence
D39: Preventive Action; actions to prevent the occurrence of similar problems in other areas | N39: `
D40: Controls; controls & self-monitoring steps to ensure continued CA/PA effectiveness
D41: Supplier to return the completed VSAC Workbook to the Vertiv auditor by the date agreed upon.
D42: Supplier to provide documented objective evidence that each CAPA has been implemented by the completion date specified.
D43: Vertiv auditor to use scoring instructions below when assigning the "After CAPA Verification" score.
D44: Scoring Instructions for Vertiv
D45: Based on evidence of the supplier's corrective action, select score that best describes level of compliance to the Requirement.
D46: 0 = NO EVIDENCE PROVIDED; CA Remains Open / Score Unchanged
D47: 40 = INSUFFICIENT EVIDENCE; CA Remains Open / Score Unchanged
D48: 60 = INSUFFICIENT EVIDENCE; CA Remains Open / Score Unchanged
D49: 70 = NO NON-COMPLIANCES; Meets Minimum Requirement / No CA required
D50: 80 = NO NON-COMPLIANCES; Exceeds Minimum Requirement / No CA required
D51: 100 = NO NON-COMPLIANCES; Excellent / Highly commendable
D52: Top
